[{"id":"medical-2-552","name":"あきらクリニック","categoryId":"medical","categoryLabel":"医疗","lat":35.675184,"lng":139.668009,"stationId":"station-003806","note":"内科　小児科　皮膚科　アレルギー科"},{"id":"medical-3-800","name":"いいだ歯科クリニック","categoryId":"medical","categoryLabel":"医疗","lat":35.686244,"lng":139.694867,"stationId":"station-003750","note":"歯科　矯正歯科　歯科口腔外科"},{"id":"medical-2-940","name":"いのくち内科クリニック","categoryId":"medical","categoryLabel":"医疗","lat":35.680369,"lng":139.682431,"stationId":"station-003764","note":"糖尿病内科　代謝内科"},{"id":"medical-3-981","name":"いわね歯科","categoryId":"medical","categoryLabel":"医疗","lat":35.697041,"lng":139.668048,"stationId":"station-003638","note":"歯科　矯正歯科　小児歯科　歯科口腔外科"},{"id":"medical-3-1222","name":"おおた歯科クリニック","categoryId":"medical","categoryLabel":"医疗","lat":35.683461,"lng":139.681723,"stationId":"station-003764","note":"歯科　矯正歯科　小児歯科　歯科口腔外科"},{"id":"medical-2-1265","name":"おがた皮フ科クリニック","categoryId":"medical","categoryLabel":"医疗","lat":35.697579,"lng":139.682659,"stationId":"station-003643","note":"皮膚科"},{"id":"medical-2-1410","name":"かおり内科クリニック","categoryId":"medical","categoryLabel":"医疗","lat":35.685444,"lng":139.690746,"stationId":"station-003764","note":"内科　リウマチ科"},{"id":"medical-2-1436","name":"かずえキッズクリニック","categoryId":"medical","categoryLabel":"医疗","lat":35.680717,"lng":139.66979,"stationId":"station-003806","note":"内科　小児科"},{"id":"medical-3-1466","name":"かとう歯科医院","categoryId":"medical","categoryLabel":"医疗","lat":35.697579,"lng":139.682659,"stationId":"station-003643","note":"歯科　矯正歯科　小児歯科　歯科口腔外科"},{"id":"medical-3-1474","name":"かどむら歯科医院","categoryId":"medical","categoryLabel":"医疗","lat":35.690354,"lng":139.671122,"stationId":"station-003688","note":"歯科　矯正歯科　小児歯科　歯科口腔外科"},{"id":"medical-3-1582","name":"きくち歯科医院","categoryId":"medical","categoryLabel":"医疗","lat":35.684356,"lng":139.688478,"stationId":"station-003764","note":"歯科　矯正歯科　小児歯科　歯科口腔外科"},{"id":"medical-2-1617","name":"きむら眼科","categoryId":"medical","categoryLabel":"医疗","lat":35.692474,"lng":139.675589,"stationId":"station-003679","note":"眼科"},{"id":"medical-2-1654","name":"くすのき診療所","categoryId":"medical","categoryLabel":"医疗","lat":35.698464,"lng":139.681603,"stationId":"station-003643","note":"内科　外科　脳神経外科　理学診療科"},{"id":"medical-2-1754","name":"くれクリニック","categoryId":"medical","categoryLabel":"医疗","lat":35.696065,"lng":139.689427,"stationId":"station-003662","note":"内科　循環器内科　消化器内科　胃腸内科　外科"},{"id":"medical-3-1986","name":"こんの歯科クリニック","categoryId":"medical","categoryLabel":"医疗","lat":35.677482,"lng":139.667047,"stationId":"station-003806","note":"歯科　矯正歯科　小児歯科　歯科口腔外科"},{"id":"medical-3-1978","name":"ごりらのはいしゃさん","categoryId":"medical","categoryLabel":"医疗","lat":35.679988,"lng":139.685744,"stationId":"station-003764","note":"歯科　矯正歯科　小児歯科"},{"id":"medical-3-2087","name":"さくら歯科クリニック","categoryId":"medical","categoryLabel":"医疗","lat":35.69482,"lng":139.667797,"stationId":"station-003638","note":"歯科　矯正歯科　小児歯科"},{"id":"medical-3-2153","name":"さとみデンタルオフィス","categoryId":"medical","categoryLabel":"医疗","lat":35.695057,"lng":139.691493,"stationId":"station-003662","note":"歯科　小児歯科"},{"id":"medical-3-2378","name":"すぎうら歯科","categoryId":"medical","categoryLabel":"医疗","lat":35.686461,"lng":139.670838,"stationId":"station-003688","note":"歯科　小児歯科"},{"id":"medical-3-2419","name":"すずき歯科診療所","categoryId":"medical","categoryLabel":"医疗","lat":35.69221,"lng":139.684086,"stationId":"station-003696","note":"歯科"},{"id":"medical-2-2426","name":"すずな皮ふ科クリニック","categoryId":"medical","categoryLabel":"医疗","lat":35.677005,"lng":139.675216,"stationId":"station-003791","note":"小児皮膚科　美容皮膚科　皮膚科　アレルギー科"},{"id":"medical-2-2427","name":"すずむら眼科","categoryId":"medical","categoryLabel":"医疗","lat":35.697171,"lng":139.667774,"stationId":"station-003638","note":"眼科"},{"id":"medical-2-2496","name":"せき眼科","categoryId":"medical","categoryLabel":"医疗","lat":35.697579,"lng":139.682659,"stationId":"station-003643","note":"眼科"},{"id":"medical-2-2725","name":"たはらレディースクリニック","categoryId":"medical","categoryLabel":"医疗","lat":35.677885,"lng":139.682503,"stationId":"station-003791","note":"産科　婦人科"},{"id":"medical-2-2737","name":"たまつ小児科医院","categoryId":"medical","categoryLabel":"医疗","lat":35.683807,"lng":139.667289,"stationId":"station-003688","note":"小児科"},{"id":"medical-2-2802","name":"つくし診療所","categoryId":"medical","categoryLabel":"医疗","lat":35.684085,"lng":139.682675,"stationId":"station-003764","note":"漢方内科　内科　皮膚科"},{"id":"medical-2-2806","name":"つじ醫院","categoryId":"medical","categoryLabel":"医疗","lat":35.675502,"lng":139.66819,"stationId":"station-003806","note":"内科　アレルギー科　皮膚科"},{"id":"medical-2-3101","name":"なかた皮フ科","categoryId":"medical","categoryLabel":"医疗","lat":35.687103,"lng":139.666887,"stationId":"station-003688","note":"皮膚科　アレルギー科"},{"id":"medical-3-3112","name":"なかの新橋歯科クリニック","categoryId":"medical","categoryLabel":"医疗","lat":35.693241,"lng":139.674173,"stationId":"station-003679","note":"歯科口腔外科　小児歯科　矯正歯科　歯科"},{"id":"medical-3-3113","name":"なかの通り歯のクリニック","categoryId":"medical","categoryLabel":"医疗","lat":35.688677,"lng":139.668678,"stationId":"station-003688","note":"歯科　小児歯科　歯科口腔外科　矯正歯科"},{"id":"medical-2-3165","name":"なまため眼科","categoryId":"medical","categoryLabel":"医疗","lat":35.697597,"lng":139.663854,"stationId":"station-003628","note":"眼科"},{"id":"medical-3-3293","name":"のむら歯科クリニック","categoryId":"medical","categoryLabel":"医疗","lat":35.68827,"lng":139.676063,"stationId":"station-003679","note":"歯科　矯正歯科　小児歯科　歯科口腔外科"},{"id":"medical-2-3360","name":"はたがやおかだ眼科","categoryId":"medical","categoryLabel":"医疗","lat":35.678388,"lng":139.677484,"stationId":"station-003791","note":"眼科"},{"id":"medical-2-3361","name":"はたがやメンタルクリニック","categoryId":"medical","categoryLabel":"医疗","lat":35.680197,"lng":139.676526,"stationId":"station-003791","note":"精神科　心療内科"},{"id":"medical-2-3363","name":"はたがや南口心療内科","categoryId":"medical","categoryLabel":"医疗","lat":35.676384,"lng":139.676923,"stationId":"station-003791","note":"漢方精神科　精神科　心療内科"},{"id":"medical-3-3362","name":"はたがや歯科","categoryId":"medical","categoryLabel":"医疗","lat":35.676384,"lng":139.676923,"stationId":"station-003791","note":"歯科　小児歯科　歯科口腔外科"},{"id":"medical-3-3364","name":"はただデンタルクリニック","categoryId":"medical","categoryLabel":"医疗","lat":35.68744,"lng":139.683355,"stationId":"station-003696","note":"歯科　歯科口腔外科"},{"id":"medical-3-3411","name":"はまだ歯科医院","categoryId":"medical","categoryLabel":"医疗","lat":35.681124,"lng":139.685697,"stationId":"station-003764","note":"歯科　矯正歯科　小児歯科　歯科口腔外科"},{"id":"medical-2-3412","name":"はまだ耳鼻咽喉科","categoryId":"medical","categoryLabel":"医疗","lat":35.692511,"lng":139.674992,"stationId":"station-003679","note":"耳鼻咽喉科"},{"id":"medical-3-3433","name":"はらだ歯科クリニック","categoryId":"medical","categoryLabel":"医疗","lat":35.679645,"lng":139.68697,"stationId":"station-003764","note":"歯科　矯正歯科　小児歯科　歯科口腔外科"},{"id":"medical-3-3470","name":"ひいらぎ歯科クリニック","categoryId":"medical","categoryLabel":"医疗","lat":35.684194,"lng":139.661231,"stationId":"station-003751","note":"歯科　矯正歯科　小児歯科　歯科口腔外科"},{"id":"medical-3-3501","name":"ひぐち歯科医院","categoryId":"medical","categoryLabel":"医疗","lat":35.693927,"lng":139.666062,"stationId":"station-003688","note":"歯科　小児歯科"},{"id":"medical-3-3651","name":"ふくだ歯科・矯正歯科","categoryId":"medical","categoryLabel":"医疗","lat":35.676375,"lng":139.672984,"stationId":"station-003791","note":"歯科　矯正歯科　小児歯科　歯科口腔外科"},{"id":"medical-3-3682","name":"ふじみ歯科","categoryId":"medical","categoryLabel":"医疗","lat":35.690893,"lng":139.667796,"stationId":"station-003688","note":"歯科　矯正歯科　小児歯科　歯科口腔外科"},{"id":"medical-2-3796","name":"ほしなこどもクリニック","categoryId":"medical","categoryLabel":"医疗","lat":35.675068,"lng":139.676506,"stationId":"station-003791","note":"小児科"},{"id":"medical-2-3885","name":"まこと小児神経クリニック","categoryId":"medical","categoryLabel":"医疗","lat":35.689167,"lng":139.685243,"stationId":"station-003696","note":"内科　小児科"},{"id":"medical-2-4064","name":"みなみ耳鼻咽喉科医院","categoryId":"medical","categoryLabel":"医疗","lat":35.67763,"lng":139.67476,"stationId":"station-003791","note":"気管食道科　耳鼻いんこう科"},{"id":"medical-3-4075","name":"みのん歯科医院","categoryId":"medical","categoryLabel":"医疗","lat":35.676109,"lng":139.667961,"stationId":"station-003806","note":"歯科　矯正歯科　小児歯科"},{"id":"medical-2-4102","name":"みやびハート＆ケアクリニック","categoryId":"medical","categoryLabel":"医疗","lat":35.698175,"lng":139.671032,"stationId":"station-003638","note":"内科　循環器内科　緩和ケア内科　糖尿病内科　内分泌内科　精神科"},{"id":"medical-3-4157","name":"むらい歯科クリニック","categoryId":"medical","categoryLabel":"医疗","lat":35.684369,"lng":139.693916,"stationId":"station-003750","note":"歯科　矯正歯科　小児歯科"},{"id":"medical-3-4180","name":"めぐみ歯科クリニック","categoryId":"medical","categoryLabel":"医疗","lat":35.688475,"lng":139.687178,"stationId":"station-003696","note":"歯科　矯正歯科"},{"id":"medical-2-4290","name":"やなだクリニック","categoryId":"medical","categoryLabel":"医疗","lat":35.686853,"lng":139.663153,"stationId":"station-003751","note":"内科　泌尿器科"},{"id":"medical-2-4302","name":"やまぎしこどもクリニック","categoryId":"medical","categoryLabel":"医疗","lat":35.697275,"lng":139.669243,"stationId":"station-003638","note":"小児科"},{"id":"medical-3-4350","name":"やよい歯科","categoryId":"medical","categoryLabel":"医疗","lat":35.686332,"lng":139.667226,"stationId":"station-003688","note":"歯科　小児歯科　歯科口腔外科"},{"id":"medical-3-4351","name":"やよい歯科","categoryId":"medical","categoryLabel":"医疗","lat":35.675961,"lng":139.661758,"stationId":"station-003806","note":"歯科"},{"id":"medical-2-4352","name":"やよい町こども医院","categoryId":"medical","categoryLabel":"医疗","lat":35.691545,"lng":139.681514,"stationId":"station-003696","note":"小児科　内科　アレルギー科"},{"id":"medical-2-4414","name":"ゆりスキンケアクリニック","categoryId":"medical","categoryLabel":"医疗","lat":35.697171,"lng":139.667774,"stationId":"station-003638","note":"美容皮膚科"},{"id":"medical-2-4629","name":"わかやま透析クリニック中野南台","categoryId":"medical","categoryLabel":"医疗","lat":35.685796,"lng":139.668259,"stationId":"station-003688","note":"腎臓内科　内科　人工透析内科"},{"id":"medical-2-416","name":"アイエスクリニック","categoryId":"medical","categoryLabel":"医疗","lat":35.693619,"lng":139.693974,"stationId":"station-003662","note":"美容皮膚科　皮膚科"},{"id":"medical-3-435","name":"アイタウンプラザデンタルオフィス","categoryId":"medical","categoryLabel":"医疗","lat":35.693509,"lng":139.687932,"stationId":"station-003662","note":"歯科　矯正歯科　小児歯科　歯科口腔外科"},{"id":"medical-2-455","name":"アイランドタワークリニック新宿","categoryId":"medical","categoryLabel":"医疗","lat":35.692699,"lng":139.692504,"stationId":"station-003662","note":"形成外科"},{"id":"medical-3-490","name":"アオイ歯科医院","categoryId":"medical","categoryLabel":"医疗","lat":35.689534,"lng":139.687713,"stationId":"station-003696","note":"歯科　矯正歯科　小児歯科"},{"id":"medical-3-702","name":"アマリ歯科クリニック","categoryId":"medical","categoryLabel":"医疗","lat":35.697256,"lng":139.682529,"stationId":"station-003643","note":"歯科　矯正歯科　小児歯科　歯科口腔外科"},{"id":"medical-3-1027","name":"ウェル西新宿デンタルクリニック","categoryId":"medical","categoryLabel":"医疗","lat":35.687234,"lng":139.694902,"stationId":"station-003690","note":"歯科　矯正歯科　歯科口腔外科　小児歯科"},{"id":"medical-3-1164","name":"エレ矯正歯科医院","categoryId":"medical","categoryLabel":"医疗","lat":35.697896,"lng":139.666051,"stationId":"station-003638","note":"矯正歯科"},{"id":"medical-3-1169","name":"エンドウ歯科医院","categoryId":"medical","categoryLabel":"医疗","lat":35.684996,"lng":139.676687,"stationId":"station-003679","note":"歯科　矯正歯科　小児歯科　歯科口腔外科"},{"id":"medical-2-1266","name":"オカトミ・クリニック","categoryId":"medical","categoryLabel":"医疗","lat":35.693766,"lng":139.668324,"stationId":"station-003688","note":"内科　小児科　産婦人科"},{"id":"medical-2-1353","name":"オペラシティクリニック","categoryId":"medical","categoryLabel":"医疗","lat":35.68299,"lng":139.686481,"stationId":"station-003764","note":"内科　漢方内科"},{"id":"medical-2-1427","name":"カシオ本社診療所","categoryId":"medical","categoryLabel":"医疗","lat":35.680936,"lng":139.684749,"stationId":"station-003764","note":"内科"},{"id":"medical-2-1734","name":"クリニック玲タケダ","categoryId":"medical","categoryLabel":"医疗","lat":35.682632,"lng":139.684571,"stationId":"station-003764","note":"神経科　内科　皮膚科　精神科　産婦人科"},{"id":"medical-1-1769","name":"クロス病院","categoryId":"medical","categoryLabel":"医疗","lat":35.677195,"lng":139.674903,"stationId":"station-003791","note":"内科　胃腸科　外科　整形外科　リハビリ科"},{"id":"medical-2-1887","name":"コスモメディカル中野クリニック","categoryId":"medical","categoryLabel":"医疗","lat":35.692634,"lng":139.67432,"stationId":"station-003679","note":"皮膚科　アレルギー科　形成外科"},{"id":"medical-3-1981","name":"コンシェル歯科クリニック新宿本院","categoryId":"medical","categoryLabel":"医疗","lat":35.688074,"lng":139.693453,"stationId":"station-003690","note":"歯科　矯正歯科　小児歯科　歯科口腔外科"},{"id":"medical-2-2016","name":"サウスタワークリニック","categoryId":"medical","categoryLabel":"医疗","lat":35.690146,"lng":139.694336,"stationId":"station-003690","note":"内科　外科　泌尿器科　眼科　耳鼻咽喉科　放射線科　整形外科"},{"id":"medical-3-2190","name":"サンブライト歯科","categoryId":"medical","categoryLabel":"医疗","lat":35.696432,"lng":139.682471,"stationId":"station-003643","note":"歯科"},{"id":"medical-2-2869","name":"テルモ株式会社　東京オフィス　医務室","categoryId":"medical","categoryLabel":"医疗","lat":35.68299,"lng":139.686481,"stationId":"station-003764","note":"内科"},{"id":"medical-3-3063","name":"ナオキ歯科クリニック","categoryId":"medical","categoryLabel":"医疗","lat":35.696754,"lng":139.68557,"stationId":"station-003643","note":"歯科"},{"id":"medical-2-3190","name":"ニキ・ハートクリニック","categoryId":"medical","categoryLabel":"医疗","lat":35.687835,"lng":139.679494,"stationId":"station-003696","note":"内科　循環器内科"},{"id":"medical-2-3246","name":"ネクストクリニック","categoryId":"medical","categoryLabel":"医疗","lat":35.698833,"lng":139.667382,"stationId":"station-003638","note":"内科　皮膚科　心療内科"},{"id":"medical-3-3404","name":"ハニー歯科","categoryId":"medical","categoryLabel":"医疗","lat":35.684991,"lng":139.686223,"stationId":"station-003764","note":"歯科　歯科口腔外科　小児歯科"},{"id":"medical-2-3408","name":"ハピネスホーム・ひなぎくの丘","categoryId":"medical","categoryLabel":"医疗","lat":35.688026,"lng":139.668019,"stationId":"station-003688","note":"内科"},{"id":"medical-2-3309","name":"ハートケア銀河クリニック","categoryId":"medical","categoryLabel":"医疗","lat":35.69706,"lng":139.680131,"stationId":"station-003643","note":"内科　神経科　精神科　心療内科"},{"id":"medical-2-3310","name":"ハートテラス中野弥生町診療所","categoryId":"medical","categoryLabel":"医疗","lat":35.685884,"lng":139.661392,"stationId":"station-003751","note":"内科"},{"id":"medical-3-3317","name":"ハーモニーウイング歯科","categoryId":"medical","categoryLabel":"医疗","lat":35.696692,"lng":139.683438,"stationId":"station-003643","note":"歯科　矯正歯科　小児歯科　歯科口腔外科"},{"id":"medical-2-3388","name":"パナソニックホームズ株式会社東日本地区（東部）健康管理室","categoryId":"medical","categoryLabel":"医疗","lat":35.688606,"lng":139.694592,"stationId":"station-003690","note":"内科"},{"id":"medical-3-3628","name":"フィールズ歯科・矯正歯科","categoryId":"medical","categoryLabel":"医疗","lat":35.679181,"lng":139.686966,"stationId":"station-003764","note":"歯科　矯正歯科　小児歯科　歯科口腔外科"},{"id":"medical-2-4204","name":"メディカル新中野","categoryId":"medical","categoryLabel":"医疗","lat":35.697661,"lng":139.667926,"stationId":"station-003638","note":"内科　小児科"},{"id":"medical-3-4220","name":"モギ歯科医院","categoryId":"medical","categoryLabel":"医疗","lat":35.683849,"lng":139.689752,"stationId":"station-003764","note":"歯科"},{"id":"medical-3-13488","name":"三上歯科医院","categoryId":"medical","categoryLabel":"医疗","lat":35.683452,"lng":139.665407,"stationId":"station-003751","note":"歯科"},{"id":"medical-3-13466","name":"三原デンタルクリニック","categoryId":"medical","categoryLabel":"医疗","lat":35.675922,"lng":139.676945,"stationId":"station-003791","note":"歯科　矯正歯科　小児歯科　歯科口腔外科"},{"id":"medical-2-13479","name":"三好医院","categoryId":"medical","categoryLabel":"医疗","lat":35.68586,"lng":139.69212,"stationId":"station-003690","note":"内科"},{"id":"medical-2-14975","name":"上田眼科","categoryId":"medical","categoryLabel":"医疗","lat":35.696432,"lng":139.682471,"stationId":"station-003643","note":"眼科"},{"id":"medical-3-17375","name":"中城まり歯科","categoryId":"medical","categoryLabel":"医疗","lat":35.697656,"lng":139.670213,"stationId":"station-003638","note":"歯科　矯正歯科　小児歯科"},{"id":"medical-3-17324","name":"中央５丁目歯科医院","categoryId":"medical","categoryLabel":"医疗","lat":35.697659,"lng":139.664826,"stationId":"station-003638","note":"歯科"},{"id":"medical-2-17470","name":"中島整形外科医院","categoryId":"medical","categoryLabel":"医疗","lat":35.692683,"lng":139.675065,"stationId":"station-003679","note":"外科　整形外科　理学診療科"},{"id":"medical-3-17453","name":"中島歯科","categoryId":"medical","categoryLabel":"医疗","lat":35.697167,"lng":139.669991,"stationId":"station-003638","note":"歯科"},{"id":"medical-3-17390","name":"中川歯科医院","categoryId":"medical","categoryLabel":"医疗","lat":35.695002,"lng":139.661674,"stationId":"station-003628","note":"歯科　小児歯科　矯正歯科　歯科口腔外科"},{"id":"medical-3-17484","name":"中平歯科医院","categoryId":"medical","categoryLabel":"医疗","lat":35.683305,"lng":139.684031,"stationId":"station-003764","note":"歯科"},{"id":"medical-3-17408","name":"中村歯科","categoryId":"medical","categoryLabel":"医疗","lat":35.696531,"lng":139.678484,"stationId":"station-003643","note":"歯科"},{"id":"medical-3-17519","name":"中野中央歯科診療室","categoryId":"medical","categoryLabel":"医疗","lat":35.699788,"lng":139.669057,"stationId":"station-003638","note":"歯科　矯正歯科　小児歯科"},{"id":"medical-3-17507","name":"中野坂上アクロスシティ歯科","categoryId":"medical","categoryLabel":"医疗","lat":35.69772,"lng":139.683406,"stationId":"station-003643","note":"歯科　矯正歯科　小児歯科　歯科口腔外科"},{"id":"medical-2-17508","name":"中野坂上クリニック","categoryId":"medical","categoryLabel":"医疗","lat":35.69723,"lng":139.677643,"stationId":"station-003643","note":"形成外科　美容外科"},{"id":"medical-3-17510","name":"中野歯科医院","categoryId":"medical","categoryLabel":"医疗","lat":35.698524,"lng":139.676222,"stationId":"station-003643","note":"歯科　矯正歯科　小児歯科"},{"id":"medical-2-17521","name":"中野訪問クリニック","categoryId":"medical","categoryLabel":"医疗","lat":35.696339,"lng":139.68486,"stationId":"station-003643","note":"内科　精神科　皮膚科　小児科"},{"id":"medical-2-17517","name":"中野診療所","categoryId":"medical","categoryLabel":"医疗","lat":35.69482,"lng":139.667797,"stationId":"station-003638","note":"内科　皮膚科　小児科　眼科"},{"id":"medical-3-10638","name":"井上歯科","categoryId":"medical","categoryLabel":"医疗","lat":35.679117,"lng":139.67758,"stationId":"station-003791","note":"歯科　小児歯科　歯科口腔外科"},{"id":"medical-3-10665","name":"井澤歯科医院","categoryId":"medical","categoryLabel":"医疗","lat":35.67783,"lng":139.686806,"stationId":"station-003764","note":"歯科"},{"id":"medical-3-4759","name":"伊井歯科クリニック","categoryId":"medical","categoryLabel":"医疗","lat":35.697339,"lng":139.67341,"stationId":"station-003638","note":"歯科　矯正歯科　小児歯科"},{"id":"medical-2-12421","name":"健康管理クリニック","categoryId":"medical","categoryLabel":"医疗","lat":35.688074,"lng":139.693453,"stationId":"station-003690","note":"心療内科"},{"id":"medical-2-16288","name":"先進会眼科　東京","categoryId":"medical","categoryLabel":"医疗","lat":35.692699,"lng":139.692504,"stationId":"station-003662","note":"眼科"},{"id":"medical-2-12667","name":"公益財団法人　日本心臓血圧研究振興会　榊原記念クリニック分院","categoryId":"medical","categoryLabel":"医疗","lat":35.688074,"lng":139.693453,"stationId":"station-003690","note":"内科　循環器科"},{"id":"medical-2-12668","name":"公益財団法人　日本心臓血圧研究振興会榊原記念クリニック","categoryId":"medical","categoryLabel":"医疗","lat":35.688074,"lng":139.693453,"stationId":"station-003690","note":"内科　外科　循環器科　小児科　末梢血管外科"},{"id":"medical-3-18738","name":"内藤歯科","categoryId":"medical","categoryLabel":"医疗","lat":35.679757,"lng":139.686169,"stationId":"station-003764","note":"歯科"},{"id":"medical-2-14419","name":"初台あらいクリニック","categoryId":"medical","categoryLabel":"医疗","lat":35.682382,"lng":139.688648,"stationId":"station-003764","note":"内科　外科　消化器外科　胃腸外科　肛門外科"},{"id":"medical-3-14420","name":"初台デンタルオフィス","categoryId":"medical","categoryLabel":"医疗","lat":35.683093,"lng":139.680603,"stationId":"station-003764","note":"歯科　矯正歯科　小児歯科　歯科口腔外科"},{"id":"medical-2-14422","name":"初台整形外科クリニック","categoryId":"medical","categoryLabel":"医疗","lat":35.68298,"lng":139.68338,"stationId":"station-003764","note":"リウマチ科　整形外科　リハビリテーション科"},{"id":"medical-2-14421","name":"初台眼科医院","categoryId":"medical","categoryLabel":"医疗","lat":35.679049,"lng":139.686745,"stationId":"station-003764","note":"眼科"},{"id":"medical-3-16504","name":"前島歯科医院","categoryId":"medical","categoryLabel":"医疗","lat":35.696846,"lng":139.687523,"stationId":"station-003643","note":"歯科　小児歯科　歯科口腔外科"},{"id":"medical-2-19887","name":"北新宿ガーデンクリニック","categoryId":"medical","categoryLabel":"医疗","lat":35.696065,"lng":139.689427,"stationId":"station-003662","note":"精神科　心療内科"},{"id":"medical-2-19931","name":"北田医院","categoryId":"medical","categoryLabel":"医疗","lat":35.683531,"lng":139.682961,"stationId":"station-003764","note":"内科　リウマチ科　放射線科"},{"id":"medical-1-4841","name":"医療法人　内藤病院","categoryId":"medical","categoryLabel":"医疗","lat":35.67951,"lng":139.685988,"stationId":"station-003764","note":"内科　呼吸器科　胃腸科　放射線科　リハビリ科"},{"id":"medical-3-4863","name":"医療法人みどり森会ライオンズ歯科初台","categoryId":"medical","categoryLabel":"医疗","lat":35.680364,"lng":139.685723,"stationId":"station-003764","note":"歯科　矯正歯科　小児歯科"},{"id":"medical-2-5149","name":"医療法人社団　なかむら整形外科","categoryId":"medical","categoryLabel":"医疗","lat":35.696723,"lng":139.668227,"stationId":"station-003638","note":"整形外科　リハビリテーション科"},{"id":"medical-2-5110","name":"医療法人社団　オリビエ会　新宿外科クリニック","categoryId":"medical","categoryLabel":"医疗","lat":35.687234,"lng":139.694902,"stationId":"station-003690","note":"外科　心臓血管外科　消化器外科"},{"id":"medical-2-5488","name":"医療法人社団　三峰会　宮下医院","categoryId":"medical","categoryLabel":"医疗","lat":35.683467,"lng":139.671479,"stationId":"station-003688","note":"内科　小児科　外科"},{"id":"medical-2-5482","name":"医療法人社団　三心会　中野なおクリニック","categoryId":"medical","categoryLabel":"医疗","lat":35.691354,"lng":139.67674,"stationId":"station-003679","note":"内科　麻酔科　心臓血管外科　老年内科　緩和ケア内科"},{"id":"medical-3-5706","name":"医療法人社団　世航会　西新宿デンタルオフィス東京","categoryId":"medical","categoryLabel":"医疗","lat":35.693743,"lng":139.686999,"stationId":"station-003696","note":"歯科　矯正歯科　小児歯科　歯科口腔外科"},{"id":"medical-2-5853","name":"医療法人社団　中村診療所","categoryId":"medical","categoryLabel":"医疗","lat":35.69201,"lng":139.66858,"stationId":"station-003688","note":"内科"},{"id":"medical-2-5924","name":"医療法人社団　二人会　クリニカル南台","categoryId":"medical","categoryLabel":"医疗","lat":35.685401,"lng":139.671303,"stationId":"station-003688","note":"皮膚科　小児科　外科　理学診療科　麻酔科　呼吸器内科　循環器内科　消化器内科　胃腸内科　糖尿病内科　代謝内科　ペインクリニック"},{"id":"medical-2-5378","name":"医療法人社団　健朗会　三五医院","categoryId":"medical","categoryLabel":"医疗","lat":35.681638,"lng":139.671199,"stationId":"station-003791","note":"内科　神経内科"},{"id":"medical-3-5801","name":"医療法人社団　創美会　いいの歯科医院","categoryId":"medical","categoryLabel":"医疗","lat":35.682479,"lng":139.669662,"stationId":"station-003688","note":"歯科　矯正歯科　小児歯科　歯科口腔外科"},{"id":"medical-2-5787","name":"医療法人社団　千房会　新中野女性クリニック","categoryId":"medical","categoryLabel":"医疗","lat":35.696672,"lng":139.668513,"stationId":"station-003638","note":"小児科　産婦人科"},{"id":"medical-1-5259","name":"医療法人社団　回心会　回心堂病院","categoryId":"medical","categoryLabel":"医疗","lat":35.67749,"lng":139.675932,"stationId":"station-003791","note":"内科　老年内科"},{"id":"medical-3-5879","name":"医療法人社団　土田歯科医院","categoryId":"medical","categoryLabel":"医疗","lat":35.685635,"lng":139.668965,"stationId":"station-003688","note":"歯科"},{"id":"medical-2-5814","name":"医療法人社団　多田町診療所","categoryId":"medical","categoryLabel":"医疗","lat":35.683499,"lng":139.666091,"stationId":"station-003751","note":"内科　呼吸器科　アレルギー科　小児科"},{"id":"medical-2-5407","name":"医療法人社団　幸芳会　藤間産婦人科医院","categoryId":"medical","categoryLabel":"医疗","lat":35.689582,"lng":139.680049,"stationId":"station-003696","note":"内科　小児科　産婦人科"},{"id":"medical-2-5416","name":"医療法人社団　広士会　陣内耳鼻咽喉科クリニック","categoryId":"medical","categoryLabel":"医疗","lat":35.675292,"lng":139.668216,"stationId":"station-003806","note":"漢方内科　耳鼻いんこう科"},{"id":"medical-2-5521","name":"医療法人社団　慈尚会　やまもと消化器内科クリニック","categoryId":"medical","categoryLabel":"医疗","lat":35.697432,"lng":139.675927,"stationId":"station-003638","note":"内科　皮膚科　外科　リハビリテーション科　消化器内科　胃腸内科"},{"id":"medical-2-5461","name":"医療法人社団　最匠会　光伸メディカルクリニック","categoryId":"medical","categoryLabel":"医疗","lat":35.696065,"lng":139.689427,"stationId":"station-003662","note":"整形外科　美容外科　リハビリテーション科　美容皮膚科　ペインクリニック内科"},{"id":"medical-2-5625","name":"医療法人社団　松和会　望星西新宿診療所","categoryId":"medical","categoryLabel":"医疗","lat":35.685345,"lng":139.688314,"stationId":"station-003764","note":"内科　泌尿器科　透析内科"},{"id":"medical-3-5514","name":"医療法人社団　歯磨きワン　高野歯科クリニック","categoryId":"medical","categoryLabel":"医疗","lat":35.697114,"lng":139.67152,"stationId":"station-003638","note":"歯科　矯正歯科　小児歯科"},{"id":"medical-2-5906","name":"医療法人社団　統合医療会ナガヤメディカルクリニック","categoryId":"medical","categoryLabel":"医疗","lat":35.697259,"lng":139.677294,"stationId":"station-003643","note":"内科　皮膚科　外科　呼吸器科　小児科"},{"id":"medical-2-6077","name":"医療法人社団　緑の森　さくらクリニック","categoryId":"medical","categoryLabel":"医疗","lat":35.692518,"lng":139.681641,"stationId":"station-003696","note":"内科　神経内科"},{"id":"medical-3-5690","name":"医療法人社団　翠聖会　パール歯科医院","categoryId":"medical","categoryLabel":"医疗","lat":35.69721,"lng":139.679061,"stationId":"station-003643","note":"歯科　矯正歯科　小児歯科　歯科口腔外科"},{"id":"medical-2-5203","name":"医療法人社団　育寿会　高橋医院","categoryId":"medical","categoryLabel":"医疗","lat":35.684132,"lng":139.668723,"stationId":"station-003688","note":"内科　皮膚科　小児科　外科"},{"id":"medical-2-5683","name":"医療法人社団　腎と水　新中野透析クリニック","categoryId":"medical","categoryLabel":"医疗","lat":35.696212,"lng":139.67432,"stationId":"station-003638","note":"外科　リハビリテーション科　循環器内科　人工透析内科"},{"id":"medical-1-5281","name":"医療法人社団　輝生会　初台リハビリテーション病院","categoryId":"medical","categoryLabel":"医疗","lat":35.68645,"lng":139.684175,"stationId":"station-003696","note":"神経内科　リハビリ科"},{"id":"medical-2-5911","name":"医療法人社団　透心会　初台クリニック","categoryId":"medical","categoryLabel":"医疗","lat":35.67894,"lng":139.687241,"stationId":"station-003764","note":"神経内科　精神科　心療内科"},{"id":"medical-2-6369","name":"医療法人社団いずみ会　堀江皮膚科医院","categoryId":"medical","categoryLabel":"医疗","lat":35.6858,"lng":139.688503,"stationId":"station-003764","note":"皮膚科"},{"id":"medical-2-6370","name":"医療法人社団いその会　あさわクリニック初台","categoryId":"medical","categoryLabel":"医疗","lat":35.681563,"lng":139.685059,"stationId":"station-003764","note":"肛門内科　内科　消化器内科　胃腸内科　アレルギー科"},{"id":"medical-2-6419","name":"医療法人社団おざき整形外科クリニック","categoryId":"medical","categoryLabel":"医疗","lat":35.683503,"lng":139.684093,"stationId":"station-003764","note":"内科　皮膚科　整形外科　リハビリテーション科"},{"id":"medical-2-6664","name":"医療法人社団はたがや協立会はたがや協立診療所","categoryId":"medical","categoryLabel":"医疗","lat":35.681119,"lng":139.675645,"stationId":"station-003791","note":"循環器科　内科"},{"id":"medical-2-6586","name":"医療法人社団ソレイユ　平澤クリニック","categoryId":"medical","categoryLabel":"医疗","lat":35.691339,"lng":139.677874,"stationId":"station-003679","note":"内科　小児科　呼吸器内科　循環器内科　消化器内科　胃腸内科"},{"id":"medical-3-6617","name":"医療法人社団デンタルケアコミュニティ　フォレストデンタル","categoryId":"medical","categoryLabel":"医疗","lat":35.695389,"lng":139.69057,"stationId":"station-003662","note":"歯科　矯正歯科　小児歯科　歯科口腔外科"},{"id":"medical-3-6738","name":"医療法人社団フロンティア　新宿フロントタワー歯科","categoryId":"medical","categoryLabel":"医疗","lat":35.696065,"lng":139.689427,"stationId":"station-003662","note":"歯科　矯正歯科　小児歯科　歯科口腔外科"},{"id":"medical-2-6744","name":"医療法人社団ペルル　マーガレットこどもクリニック","categoryId":"medical","categoryLabel":"医疗","lat":35.680834,"lng":139.689192,"stationId":"station-003764","note":"小児科　児童精神科"},{"id":"medical-2-6794","name":"医療法人社団メディカルフェニックス　メディカルスキャニング新宿","categoryId":"medical","categoryLabel":"医疗","lat":35.694523,"lng":139.690925,"stationId":"station-003662","note":"内科　放射線科"},{"id":"medical-3-9414","name":"医療法人社団中七会　中山歯科クリニック","categoryId":"medical","categoryLabel":"医疗","lat":35.690603,"lng":139.665473,"stationId":"station-003688","note":"歯科　小児歯科　歯科口腔外科"},{"id":"medical-3-7263","name":"医療法人社団京隆会　おくはた歯科クリニック","categoryId":"medical","categoryLabel":"医疗","lat":35.681912,"lng":139.675229,"stationId":"station-003791","note":"歯科　矯正歯科　小児歯科　歯科口腔外科"},{"id":"medical-2-8752","name":"医療法人社団仁友会　仁友クリニック","categoryId":"medical","categoryLabel":"医疗","lat":35.695865,"lng":139.682161,"stationId":"station-003643","note":"内科　呼吸器科　アレルギー科　小児科"},{"id":"medical-3-8563","name":"医療法人社団伸永会　歯科中橋","categoryId":"medical","categoryLabel":"医疗","lat":35.692512,"lng":139.675002,"stationId":"station-003679","note":"歯科"},{"id":"medical-3-10064","name":"医療法人社団佑健会新宿ＫＴ歯科・矯正歯科","categoryId":"medical","categoryLabel":"医疗","lat":35.695349,"lng":139.688599,"stationId":"station-003662","note":"歯科　矯正歯科　小児歯科　歯科口腔外科"},{"id":"medical-2-7576","name":"医療法人社団健宝会　小川医院","categoryId":"medical","categoryLabel":"医疗","lat":35.678911,"lng":139.677547,"stationId":"station-003791","note":"消化器科　内科　小児科"},{"id":"medical-3-7571","name":"医療法人社団健美会山田歯科医院","categoryId":"medical","categoryLabel":"医疗","lat":35.676475,"lng":139.67344,"stationId":"station-003791","note":"歯科　矯正歯科　歯科口腔外科"},{"id":"medical-3-7562","name":"医療法人社団健青会銀座青山Ｙｏｕ矯正歯科　新宿医院","categoryId":"medical","categoryLabel":"医疗","lat":35.687087,"lng":139.693883,"stationId":"station-003690","note":"歯科　矯正歯科　小児歯科　歯科口腔外科"},{"id":"medical-2-10084","name":"医療法人社団優久会　根本医院","categoryId":"medical","categoryLabel":"医疗","lat":35.689285,"lng":139.685894,"stationId":"station-003696","note":"内科　糖尿病内科　小児科"},{"id":"medical-2-10099","name":"医療法人社団優祉会　新中野皮膚科クリニック","categoryId":"medical","categoryLabel":"医疗","lat":35.697675,"lng":139.670384,"stationId":"station-003638","note":"皮膚科　形成外科　アレルギー科　小児皮膚科　美容皮膚科"},{"id":"medical-3-10119","name":"医療法人社団優誠会　グリーンタワー歯科","categoryId":"medical","categoryLabel":"医疗","lat":35.692293,"lng":139.689647,"stationId":"station-003690","note":"歯科"},{"id":"medical-2-8428","name":"医療法人社団勝和会　土田整形外科","categoryId":"medical","categoryLabel":"医疗","lat":35.680027,"lng":139.670192,"stationId":"station-003806","note":"皮膚科　外科　整形外科　リハビリテーション科　放射線科"},{"id":"medical-2-6932","name":"医療法人社団医幸会　喜多村脳神経クリニック","categoryId":"medical","categoryLabel":"医疗","lat":35.688074,"lng":139.693453,"stationId":"station-003690","note":"神経内科　脳神経外科"},{"id":"medical-2-6952","name":"医療法人社団医鍼会　蔡内科クリニック","categoryId":"medical","categoryLabel":"医疗","lat":35.680752,"lng":139.686616,"stationId":"station-003764","note":"胃腸科　内科　皮膚科　リハビリテーション科"},{"id":"medical-2-9702","name":"医療法人社団博和会　山本クリニック","categoryId":"medical","categoryLabel":"医疗","lat":35.686585,"lng":139.672516,"stationId":"station-003679","note":"内科　小児科　外科　放射線科　消化器内科　胃腸内科　呼吸器内科"},{"id":"medical-2-9703","name":"医療法人社団博和会　山本眼科クリニック","categoryId":"medical","categoryLabel":"医疗","lat":35.686585,"lng":139.672516,"stationId":"station-003679","note":"眼科"},{"id":"medical-2-9673","name":"医療法人社団博桜会　ふるかわレディースクリニック","categoryId":"medical","categoryLabel":"医疗","lat":35.695096,"lng":139.692834,"stationId":"station-003662","note":"産婦人科　性感染症婦人科　皮膚科　内科"},{"id":"medical-2-10417","name":"医療法人社団和孝会　荻原整形外科","categoryId":"medical","categoryLabel":"医疗","lat":35.683691,"lng":139.682979,"stationId":"station-003764","note":"内科　リウマチ科　小児科　整形外科　リハビリテーション科"},{"id":"medical-2-7980","name":"医療法人社団咲良会　初台耳鼻咽喉科クリニック","categoryId":"medical","categoryLabel":"医疗","lat":35.682632,"lng":139.684571,"stationId":"station-003764","note":"耳鼻いんこう科"},{"id":"medical-2-9196","name":"医療法人社団善仁会　ヘルチェックレディース新宿クリニック","categoryId":"medical","categoryLabel":"医疗","lat":35.69157,"lng":139.691072,"stationId":"station-003690","note":"女性内科　婦人科"},{"id":"medical-2-9198","name":"医療法人社団善仁会　新宿西口ヘルチェッククリニック","categoryId":"medical","categoryLabel":"医疗","lat":35.686982,"lng":139.694094,"stationId":"station-003690","note":"内科　婦人科"},{"id":"medical-3-8093","name":"医療法人社団四瑛会　新宿パークタワー歯科","categoryId":"medical","categoryLabel":"医疗","lat":35.685444,"lng":139.690746,"stationId":"station-003764","note":"歯科　小児歯科　矯正歯科　歯科口腔外科"},{"id":"medical-2-7726","name":"医療法人社団宏彩会　西新宿コンシェリアクリニック","categoryId":"medical","categoryLabel":"医疗","lat":35.692617,"lng":139.687396,"stationId":"station-003696","note":"心療内科　漢方精神科"},{"id":"medical-3-7730","name":"医療法人社団宏清会　ＮＳビル歯科","categoryId":"medical","categoryLabel":"医疗","lat":35.688074,"lng":139.693453,"stationId":"station-003690","note":"歯科"},{"id":"medical-2-8448","name":"医療法人社団尚高会西新宿きさらぎクリニック","categoryId":"medical","categoryLabel":"医疗","lat":35.692682,"lng":139.691119,"stationId":"station-003662","note":"内科　循環器内科　消化器内科　胃腸内科"},{"id":"medical-2-9882","name":"医療法人社団峰岸医院","categoryId":"medical","categoryLabel":"医疗","lat":35.691681,"lng":139.686299,"stationId":"station-003696","note":"産婦人科"},{"id":"medical-2-7776","name":"医療法人社団広士会　新中野耳鼻咽喉科クリニック","categoryId":"medical","categoryLabel":"医疗","lat":35.697275,"lng":139.669243,"stationId":"station-003638","note":"耳鼻いんこう科　漢方内科"},{"id":"medical-3-7793","name":"医療法人社団康治会　片平歯科クリニック","categoryId":"medical","categoryLabel":"医疗","lat":35.685069,"lng":139.692996,"stationId":"station-003750","note":"歯科"},{"id":"medical-2-7813","name":"医療法人社団康翔勝会　堤耳鼻咽喉科医院","categoryId":"medical","categoryLabel":"医疗","lat":35.69563,"lng":139.680532,"stationId":"station-003643","note":"耳鼻咽喉科"},{"id":"medical-3-7817","name":"医療法人社団弘快会　新宿オークタワー歯科クリニック","categoryId":"medical","categoryLabel":"医疗","lat":35.693904,"lng":139.690625,"stationId":"station-003662","note":"歯科　矯正歯科　小児歯科　歯科口腔外科"},{"id":"medical-2-8588","name":"医療法人社団心?会　大倉診療所","categoryId":"medical","categoryLabel":"医疗","lat":35.692324,"lng":139.675445,"stationId":"station-003679","note":"漢方内科　精神科"},{"id":"medical-3-8594","name":"医療法人社団心幸会　ササマ歯科クリニック","categoryId":"medical","categoryLabel":"医疗","lat":35.679366,"lng":139.693806,"stationId":"station-003778","note":"歯科"},{"id":"medical-3-7392","name":"医療法人社団恵奈会　アイランドデンタルクリニックエトー歯科","categoryId":"medical","categoryLabel":"医疗","lat":35.692699,"lng":139.692504,"stationId":"station-003662","note":"歯科　矯正歯科　歯科口腔外科"},{"id":"medical-2-6884","name":"医療法人社団愛州会　アイランド耳鼻咽喉科","categoryId":"medical","categoryLabel":"医疗","lat":35.692699,"lng":139.692504,"stationId":"station-003662","note":"耳鼻いんこう科"},{"id":"medical-2-7423","name":"医療法人社団慶潤会　ＫＤＤＩビルクリニック","categoryId":"medical","categoryLabel":"医疗","lat":35.687918,"lng":139.694852,"stationId":"station-003690","note":"内視鏡内科　内科　呼吸器内科　糖尿病内科　代謝内科　精神科"},{"id":"medical-2-7424","name":"医療法人社団慶潤会新都心十二社クリニック","categoryId":"medical","categoryLabel":"医疗","lat":35.693743,"lng":139.686999,"stationId":"station-003696","note":"内科　糖尿病内科　循環器内科"},{"id":"medical-2-7428","name":"医療法人社団慶照会　幡ヶ谷内科クリニック","categoryId":"medical","categoryLabel":"医疗","lat":35.67796,"lng":139.675277,"stationId":"station-003791","note":"内科　循環器内科　消化器内科　胃腸内科"},{"id":"medical-2-7454","name":"医療法人社団慶翔会新宿眼科クリニック","categoryId":"medical","categoryLabel":"医疗","lat":35.696065,"lng":139.689427,"stationId":"station-003662","note":"眼科"},{"id":"medical-2-8836","name":"医療法人社団成山会　楠樹記念クリニック","categoryId":"medical","categoryLabel":"医疗","lat":35.69133,"lng":139.692871,"stationId":"station-003690","note":"内科　放射線科　婦人科"},{"id":"medical-2-9377","name":"医療法人社団拓研会　岩瀬内科循環器科クリニック","categoryId":"medical","categoryLabel":"医疗","lat":35.675292,"lng":139.668216,"stationId":"station-003806","note":"内科　循環器内科"},{"id":"medical-2-8633","name":"医療法人社団新友会　プラザ３０階クリニック","categoryId":"medical","categoryLabel":"医疗","lat":35.690146,"lng":139.694336,"stationId":"station-003690","note":"内科　消化器内科　乳腺外科　眼科　婦人科　皮膚科"},{"id":"medical-2-8614","name":"医療法人社団新宿レディースクリニック会　新宿レディースクリニック","categoryId":"medical","categoryLabel":"医疗","lat":35.692699,"lng":139.692504,"stationId":"station-003662","note":"産婦人科　麻酔科"},{"id":"medical-2-6902","name":"医療法人社団旭洋会　鈴木医院","categoryId":"medical","categoryLabel":"医疗","lat":35.682504,"lng":139.680944,"stationId":"station-003764","note":"内科　外科"},{"id":"medical-3-7860","name":"医療法人社団晃香会　新中野歯科クリニック","categoryId":"medical","categoryLabel":"医疗","lat":35.697661,"lng":139.667926,"stationId":"station-003638","note":"歯科　矯正歯科　小児歯科"},{"id":"medical-3-10178","name":"医療法人社団有心会　クリア歯科新宿モノリス院","categoryId":"medical","categoryLabel":"医疗","lat":35.688606,"lng":139.694592,"stationId":"station-003690","note":"歯科　矯正歯科　小児歯科　歯科口腔外科"},{"id":"medical-2-9707","name":"医療法人社団柏裕会　今野整形外科内科","categoryId":"medical","categoryLabel":"医疗","lat":35.694373,"lng":139.694743,"stationId":"station-003662","note":"整形外科　内科　リハビリテーション科"},{"id":"medical-2-9810","name":"医療法人社団楓心会　おおぬき耳鼻咽喉科","categoryId":"medical","categoryLabel":"医疗","lat":35.696065,"lng":139.689427,"stationId":"station-003662","note":"耳鼻いんこう科"},{"id":"medical-2-7977","name":"医療法人社団榊原厚生会　新宿三井ビルクリニック","categoryId":"medical","categoryLabel":"医疗","lat":35.691709,"lng":139.693956,"stationId":"station-003690","note":"内科　循環器内科　消化器内科　呼吸器内科　皮膚科　婦人科"},{"id":"medical-2-7976","name":"医療法人社団榊原厚生会　新宿ＮＳビルクリニック","categoryId":"medical","categoryLabel":"医疗","lat":35.688074,"lng":139.693453,"stationId":"station-003690","note":"内科　消化器科　循環器科　外科"},{"id":"medical-2-7979","name":"医療法人社団榊原厚生会新宿三井ビルクリニック分院","categoryId":"medical","categoryLabel":"医疗","lat":35.691709,"lng":139.693956,"stationId":"station-003690","note":"内科　消化器科　循環器科"},{"id":"medical-2-8283","name":"医療法人社団樹仁会　森医院","categoryId":"medical","categoryLabel":"医疗","lat":35.682867,"lng":139.683297,"stationId":"station-003764","note":"肛門科　内視鏡内　外科　アレルギー疾患内科　アレルギー疾患外科　内科　呼吸器内科　循環器内科　消化器内科　胃腸内科　皮膚科　小児科　外科　呼吸器外科　肛門外科　耳鼻いんこう科"},{"id":"medical-3-8151","name":"医療法人社団歯友会　赤羽歯科（新宿）","categoryId":"medical","categoryLabel":"医疗","lat":35.69133,"lng":139.692871,"stationId":"station-003690","note":"歯科　矯正歯科　小児歯科　歯科口腔外科"},{"id":"medical-2-7037","name":"医療法人社団永康会　新宿西口腎クリニック","categoryId":"medical","categoryLabel":"医疗","lat":35.692699,"lng":139.692504,"stationId":"station-003662","note":"人工透析内科"},{"id":"medical-2-7886","name":"医療法人社団浩悠会　田沼内科・小児科医院","categoryId":"medical","categoryLabel":"医疗","lat":35.695485,"lng":139.664422,"stationId":"station-003638","note":"内科　小児科"},{"id":"medical-3-9458","name":"医療法人社団滴翠会　山田歯科医院","categoryId":"medical","categoryLabel":"医疗","lat":35.69839,"lng":139.673685,"stationId":"station-003638","note":"歯科　矯正歯科　小児歯科　歯科口腔外科"},{"id":"medical-2-8079","name":"医療法人社団燦燦会　中野サンクリニック","categoryId":"medical","categoryLabel":"医疗","lat":35.698089,"lng":139.684328,"stationId":"station-003643","note":"内科"},{"id":"medical-3-7303","name":"医療法人社団玉翔会初台ＧＴ歯科","categoryId":"medical","categoryLabel":"医疗","lat":35.678418,"lng":139.686838,"stationId":"station-003764","note":"歯科　矯正歯科　小児歯科　歯科口腔外科"},{"id":"medical-3-8680","name":"医療法人社団真立会　はたの歯科医院","categoryId":"medical","categoryLabel":"医疗","lat":35.680105,"lng":139.693302,"stationId":"station-003778","note":"歯科　歯科口腔外科"},{"id":"medical-3-7601","name":"医療法人社団研整会　草間歯科医院","categoryId":"medical","categoryLabel":"医疗","lat":35.690209,"lng":139.685757,"stationId":"station-003696","note":"歯科　歯科口腔外科"},{"id":"medical-3-7600","name":"医療法人社団研整会　西新宿歯科クリニック","categoryId":"medical","categoryLabel":"医疗","lat":35.690209,"lng":139.685757,"stationId":"station-003696","note":"歯科　矯正歯科　小児歯科"},{"id":"medical-3-9857","name":"医療法人社団碧心堂　やすふみ歯科クリニック","categoryId":"medical","categoryLabel":"医疗","lat":35.675537,"lng":139.677982,"stationId":"station-003791","note":"歯科　矯正歯科"},{"id":"medical-2-9135","name":"医療法人社団碩和会　下平レディスクリニック","categoryId":"medical","categoryLabel":"医疗","lat":35.698554,"lng":139.660608,"stationId":"station-003628","note":"内科　産婦人科"},{"id":"medical-3-9832","name":"医療法人社団福真会　寺前歯科","categoryId":"medical","categoryLabel":"医疗","lat":35.69157,"lng":139.691072,"stationId":"station-003690","note":"歯科　口腔外科歯科"},{"id":"medical-3-8783","name":"医療法人社団翠聖会　新宿西口歯科医院","categoryId":"medical","categoryLabel":"医疗","lat":35.691709,"lng":139.693956,"stationId":"station-003690","note":"歯科　矯正歯科　小児歯科　歯科口腔外科"},{"id":"medical-3-8997","name":"医療法人社団聖恒会　渋谷ほんまち歯科クリニック","categoryId":"medical","categoryLabel":"医疗","lat":35.684267,"lng":139.684678,"stationId":"station-003764","note":"歯科　小児歯科　歯科口腔外科"},{"id":"medical-3-9011","name":"医療法人社団聖悠会　新宿新都心歯科口腔外科クリニック","categoryId":"medical","categoryLabel":"医疗","lat":35.6947,"lng":139.692638,"stationId":"station-003662","note":"歯科　矯正歯科　小児歯科　歯科口腔外科"},{"id":"medical-3-10372","name":"医療法人社団臨学会　初台歯科医院","categoryId":"medical","categoryLabel":"医疗","lat":35.683887,"lng":139.682786,"stationId":"station-003764","note":"歯科　小児歯科"},{"id":"medical-2-9640","name":"医療法人社団虹耀会　中野坂上米沢医院","categoryId":"medical","categoryLabel":"医疗","lat":35.697486,"lng":139.680235,"stationId":"station-003643","note":"内科　皮膚科　小児科　消化器内視鏡科"},{"id":"medical-2-9057","name":"医療法人社団誠船會　船戸耳鼻咽喉科医院","categoryId":"medical","categoryLabel":"医疗","lat":35.697156,"lng":139.671423,"stationId":"station-003638","note":"耳鼻咽喉科"},{"id":"medical-2-10306","name":"医療法人社団隆津会　辻整形外科","categoryId":"medical","categoryLabel":"医疗","lat":35.676104,"lng":139.677788,"stationId":"station-003791","note":"整形外科　リハビリテーション科"},{"id":"medical-3-10307","name":"医療法人社団隆美会　川口歯科診療所","categoryId":"medical","categoryLabel":"医疗","lat":35.692699,"lng":139.692504,"stationId":"station-003662","note":"歯科　小児歯科　歯科口腔外科"},{"id":"medical-2-7620","name":"医療法人社団顕彬会　伊藤外科内科医院","categoryId":"medical","categoryLabel":"医疗","lat":35.691221,"lng":139.686906,"stationId":"station-003696","note":"内科　胃腸科　外科"},{"id":"medical-2-6128","name":"医療法人社団ＡＹＵＭＩ　方南みどりクリニック","categoryId":"medical","categoryLabel":"医疗","lat":35.678529,"lng":139.662207,"stationId":"station-003751","note":"内科　消化器内科　内視鏡内科"},{"id":"medical-2-6129","name":"医療法人社団ＡＹＵＭＩ新宿内視鏡クリニック","categoryId":"medical","categoryLabel":"医疗","lat":35.690608,"lng":139.68654,"stationId":"station-003696","note":"消化器内科　胃腸内科　内科　内視鏡内科"},{"id":"medical-3-6186","name":"医療法人社団ＩＴＳ　東京オペラシティ歯科","categoryId":"medical","categoryLabel":"医疗","lat":35.68299,"lng":139.686481,"stationId":"station-003764","note":"歯科"},{"id":"medical-3-6303","name":"医療法人社団ＴＭＴ会　ティーエムティーデンタルクリニック","categoryId":"medical","categoryLabel":"医疗","lat":35.682088,"lng":139.674993,"stationId":"station-003791","note":"歯科　小児歯科　歯科口腔外科"},{"id":"medical-2-6312","name":"医療法人社団ＷＨＡ　さかうえ整形・形成外科クリニック","categoryId":"medical","categoryLabel":"医疗","lat":35.696432,"lng":139.682471,"stationId":"station-003643","note":"内科　皮膚科　整形外科　形成外科　美容外科　理学診療科"},{"id":"medical-1-4901","name":"医療法人財団　圭友会　小原病院","categoryId":"medical","categoryLabel":"医疗","lat":35.696961,"lng":139.678165,"stationId":"station-003643","note":"内科"},{"id":"medical-3-18792","name":"南中野小川歯科クリニック","categoryId":"medical","categoryLabel":"医疗","lat":35.688168,"lng":139.672559,"stationId":"station-003679","note":"歯科　矯正歯科　小児歯科"},{"id":"medical-2-18786","name":"南台寺尾クリニック　内科・小児科","categoryId":"medical","categoryLabel":"医疗","lat":35.683452,"lng":139.665407,"stationId":"station-003751","note":"内科　小児科　循環器内科"},{"id":"medical-2-18804","name":"南部すこやか福祉センター","categoryId":"medical","categoryLabel":"医疗","lat":35.688103,"lng":139.668501,"stationId":"station-003688","note":"内科　歯科"},{"id":"medical-2-12450","name":"原クリニック","categoryId":"medical","categoryLabel":"医疗","lat":35.686332,"lng":139.667226,"stationId":"station-003688","note":"内科　外科　胃腸科"},{"id":"medical-2-13569","name":"参宮橋こころのクリニック","categoryId":"medical","categoryLabel":"医疗","lat":35.678894,"lng":139.691883,"stationId":"station-003778","note":"児童精神科　精神科　心療内科"},{"id":"medical-3-13570","name":"参宮橋デンタルクリニック","categoryId":"medical","categoryLabel":"医疗","lat":35.677889,"lng":139.691976,"stationId":"station-003778","note":"歯科　矯正歯科　小児歯科　歯科口腔外科"},{"id":"medical-2-13572","name":"参宮橋整形外科・内科","categoryId":"medical","categoryLabel":"医疗","lat":35.677848,"lng":139.69233,"stationId":"station-003778","note":"内科　糖尿病内科　代謝内科　皮膚科　整形外科　リハビリテーション科"},{"id":"medical-2-13574","name":"参宮橋皮フ科松窪クリニック","categoryId":"medical","categoryLabel":"医疗","lat":35.67828,"lng":139.692879,"stationId":"station-003778","note":"皮膚科"},{"id":"medical-3-13571","name":"参宮橋駅前歯科","categoryId":"medical","categoryLabel":"医疗","lat":35.678531,"lng":139.69309,"stationId":"station-003778","note":"歯科　矯正歯科　小児歯科　歯科口腔外科"},{"id":"medical-2-11804","name":"吉田内科クリニック","categoryId":"medical","categoryLabel":"医疗","lat":35.696653,"lng":139.665803,"stationId":"station-003638","note":"内科　循環器科　小児科"},{"id":"medical-2-11780","name":"吉田産婦人科クリニック","categoryId":"medical","categoryLabel":"医疗","lat":35.679931,"lng":139.670528,"stationId":"station-003791","note":"産科　婦人科"},{"id":"medical-2-20724","name":"和光診療所","categoryId":"medical","categoryLabel":"医疗","lat":35.694394,"lng":139.660361,"stationId":"station-003628","note":"内科　小児科　眼科　皮膚科"},{"id":"medical-2-20747","name":"和田整形外科クリニック","categoryId":"medical","categoryLabel":"医疗","lat":35.675292,"lng":139.668216,"stationId":"station-003806","note":"内科　整形外科　リハビリテーション科　皮膚科　リウマチ科"},{"id":"medical-3-17675","name":"坪井歯科クリニック","categoryId":"medical","categoryLabel":"医疗","lat":35.692634,"lng":139.67432,"stationId":"station-003679","note":"歯科"},{"id":"medical-3-17679","name":"坪田歯科医院","categoryId":"medical","categoryLabel":"医疗","lat":35.675824,"lng":139.67674,"stationId":"station-003791","note":"歯科　小児歯科"},{"id":"medical-2-18506","name":"堂野前医院","categoryId":"medical","categoryLabel":"医疗","lat":35.689703,"lng":139.673309,"stationId":"station-003679","note":"精神科"},{"id":"medical-2-18000","name":"塔ノ山医院","categoryId":"medical","categoryLabel":"医疗","lat":35.69991,"lng":139.681821,"stationId":"station-003643","note":"内科　皮膚科　リウマチ科　小児科　理学診療科"},{"id":"medical-2-16693","name":"多田小児クリニック","categoryId":"medical","categoryLabel":"医疗","lat":35.691328,"lng":139.666474,"stationId":"station-003688","note":"小児科　小児心療内科　思春期内科　アレルギー科"},{"id":"medical-3-17012","name":"大庭歯科医院","categoryId":"medical","categoryLabel":"医疗","lat":35.687146,"lng":139.672055,"stationId":"station-003679","note":"歯科　小児歯科"},{"id":"medical-2-16912","name":"大成建設株式会社　診療室分室","categoryId":"medical","categoryLabel":"医疗","lat":35.693904,"lng":139.690625,"stationId":"station-003662","note":"内科"},{"id":"medical-3-16829","name":"大月歯科医院","categoryId":"medical","categoryLabel":"医疗","lat":35.681891,"lng":139.688038,"stationId":"station-003764","note":"歯科"},{"id":"medical-2-4752","name":"安藤皮フ科美容外科","categoryId":"medical","categoryLabel":"医疗","lat":35.691368,"lng":139.675935,"stationId":"station-003679","note":"皮膚科　美容外科　美容皮膚科"},{"id":"medical-3-11938","name":"宮内歯科医院","categoryId":"medical","categoryLabel":"医疗","lat":35.687072,"lng":139.674644,"stationId":"station-003679","note":"歯科"},{"id":"medical-2-11944","name":"宮本医院","categoryId":"medical","categoryLabel":"医疗","lat":35.683588,"lng":139.676351,"stationId":"station-003791","note":"内科"},{"id":"medical-3-11956","name":"宮澤歯科医院","categoryId":"medical","categoryLabel":"医疗","lat":35.686419,"lng":139.684398,"stationId":"station-003696","note":"歯科　小児歯科"},{"id":"medical-2-19474","name":"富士ゼロックス東京株式会社　健康推進室","categoryId":"medical","categoryLabel":"医疗","lat":35.692293,"lng":139.689647,"stationId":"station-003690","note":"内科"},{"id":"medical-2-19480","name":"富士見クリニック","categoryId":"medical","categoryLabel":"医疗","lat":35.690432,"lng":139.665896,"stationId":"station-003688","note":"内科　脳神経外科"},{"id":"medical-2-13941","name":"寺田内科医院","categoryId":"medical","categoryLabel":"医疗","lat":35.697467,"lng":139.675752,"stationId":"station-003638","note":"内科　皮膚科"},{"id":"medical-2-14615","name":"小島クリニック","categoryId":"medical","categoryLabel":"医疗","lat":35.675844,"lng":139.66863,"stationId":"station-003806","note":"理学診療科　内科　整形外科　麻酔科"},{"id":"medical-3-14685","name":"小林歯科クリニック","categoryId":"medical","categoryLabel":"医疗","lat":35.692661,"lng":139.681734,"stationId":"station-003696","note":"歯科"},{"id":"medical-3-14697","name":"小林歯科医院","categoryId":"medical","categoryLabel":"医疗","lat":35.69661,"lng":139.666079,"stationId":"station-003638","note":"歯科"},{"id":"medical-3-14704","name":"小林歯科医院","categoryId":"medical","categoryLabel":"医疗","lat":35.69252,"lng":139.66058,"stationId":"station-003628","note":"歯科　矯正歯科　小児歯科　歯科口腔外科"},{"id":"medical-2-14481","name":"小栗医院","categoryId":"medical","categoryLabel":"医疗","lat":35.681563,"lng":139.685059,"stationId":"station-003764","note":"皮膚科"},{"id":"medical-3-14643","name":"小椋歯科クリニック","categoryId":"medical","categoryLabel":"医疗","lat":35.695865,"lng":139.681683,"stationId":"station-003643","note":"歯科"},{"id":"medical-3-14591","name":"小池歯科医院","categoryId":"medical","categoryLabel":"医疗","lat":35.697435,"lng":139.660697,"stationId":"station-003628","note":"歯科　小児歯科　歯科口腔外科"},{"id":"medical-2-14560","name":"小泉クリニック","categoryId":"medical","categoryLabel":"医疗","lat":35.67567,"lng":139.67609,"stationId":"station-003791","note":"血管外科　内科　循環器内科　外科"},{"id":"medical-3-14663","name":"小野田歯科医院","categoryId":"medical","categoryLabel":"医疗","lat":35.689822,"lng":139.681489,"stationId":"station-003696","note":"歯科　小児歯科"},{"id":"medical-3-13642","name":"山崎歯科","categoryId":"medical","categoryLabel":"医疗","lat":35.692464,"lng":139.674563,"stationId":"station-003679","note":"歯科"},{"id":"medical-3-13650","name":"山崎歯科医院","categoryId":"medical","categoryLabel":"医疗","lat":35.676611,"lng":139.67673,"stationId":"station-003791","note":"歯科　矯正歯科　小児歯科"},{"id":"medical-3-13610","name":"山形歯科医院","categoryId":"medical","categoryLabel":"医疗","lat":35.694675,"lng":139.69279,"stationId":"station-003662","note":"歯科　小児歯科　歯科口腔外科"},{"id":"medical-3-13747","name":"山本歯科医院","categoryId":"medical","categoryLabel":"医疗","lat":35.682245,"lng":139.665901,"stationId":"station-003751","note":"歯科　矯正歯科　小児歯科　歯科口腔外科"},{"id":"medical-3-13755","name":"山本歯科医院","categoryId":"medical","categoryLabel":"医疗","lat":35.67648,"lng":139.661118,"stationId":"station-003830","note":"歯科　矯正歯科"},{"id":"medical-2-13711","name":"山田内科","categoryId":"medical","categoryLabel":"医疗","lat":35.676768,"lng":139.662234,"stationId":"station-003806","note":"内科　小児科"},{"id":"medical-2-13763","name":"山脇診療所","categoryId":"medical","categoryLabel":"医疗","lat":35.678943,"lng":139.692252,"stationId":"station-003778","note":"内科　皮膚科　外科　泌尿器科　整形外科　リハビリテーション科　放射線科"},{"id":"medical-3-11007","name":"岡歯科医院","categoryId":"medical","categoryLabel":"医疗","lat":35.682382,"lng":139.688648,"stationId":"station-003764","note":"歯科　矯正歯科"},{"id":"medical-3-11025","name":"岡田歯科医院","categoryId":"medical","categoryLabel":"医疗","lat":35.688161,"lng":139.666415,"stationId":"station-003688","note":"歯科"},{"id":"medical-3-11601","name":"岩田デンタルオフィス","categoryId":"medical","categoryLabel":"医疗","lat":35.697873,"lng":139.676902,"stationId":"station-003643","note":"歯科　歯科口腔外科　矯正歯科　小児歯科"},{"id":"medical-3-16353","name":"川戸医院歯科","categoryId":"medical","categoryLabel":"医疗","lat":35.681215,"lng":139.687257,"stationId":"station-003764","note":"歯科"},{"id":"medical-2-17685","name":"帝京整形外科クリニック","categoryId":"medical","categoryLabel":"医疗","lat":35.681316,"lng":139.678583,"stationId":"station-003791","note":"リウマチ科　整形外科　リハビリテーション科"},{"id":"medical-2-19094","name":"幡ケ谷さかえ整形外科クリニック","categoryId":"medical","categoryLabel":"医疗","lat":35.677728,"lng":139.67751,"stationId":"station-003791","note":"リウマチ科　整形外科　リハビリテーション科"},{"id":"medical-3-19095","name":"幡ヶ谷わく島歯科","categoryId":"medical","categoryLabel":"医疗","lat":35.680449,"lng":139.67624,"stationId":"station-003791","note":"歯科　矯正歯科　小児歯科　歯科口腔外科"},{"id":"medical-2-19100","name":"幡ヶ谷内分泌内科クリニック","categoryId":"medical","categoryLabel":"医疗","lat":35.679069,"lng":139.678914,"stationId":"station-003791","note":"内分泌内科"},{"id":"medical-2-19101","name":"幡ヶ谷皮フ科クリニック","categoryId":"medical","categoryLabel":"医疗","lat":35.675329,"lng":139.678183,"stationId":"station-003791","note":"皮膚科"},{"id":"medical-2-19099","name":"幡ヶ谷眼科","categoryId":"medical","categoryLabel":"医疗","lat":35.677728,"lng":139.67751,"stationId":"station-003791","note":"眼科"},{"id":"medical-2-19097","name":"幡ヶ谷駅前クリニック","categoryId":"medical","categoryLabel":"医疗","lat":35.677673,"lng":139.67716,"stationId":"station-003791","note":"精神科　心療内科"},{"id":"medical-3-19098","name":"幡ヶ谷駅前歯科","categoryId":"medical","categoryLabel":"医疗","lat":35.678164,"lng":139.677523,"stationId":"station-003791","note":"歯科　矯正歯科　小児歯科　歯科口腔外科"},{"id":"medical-3-19720","name":"平野歯科医院","categoryId":"medical","categoryLabel":"医疗","lat":35.678137,"lng":139.667256,"stationId":"station-003806","note":"歯科"},{"id":"medical-2-20341","name":"弥生ファーストクリニック","categoryId":"medical","categoryLabel":"医疗","lat":35.696432,"lng":139.682471,"stationId":"station-003643","note":"内科　放射線科　循環器内科　消化器内科　胃腸内科"},{"id":"medical-3-12617","name":"後藤歯科医院","categoryId":"medical","categoryLabel":"医疗","lat":35.677285,"lng":139.675969,"stationId":"station-003791","note":"歯科"},{"id":"medical-2-18522","name":"徳山医院","categoryId":"medical","categoryLabel":"医疗","lat":35.699275,"lng":139.675887,"stationId":"station-003638","note":"内科"},{"id":"medical-3-15658","name":"成子坂歯科イムラクリニック","categoryId":"medical","categoryLabel":"医疗","lat":35.69882,"lng":139.689495,"stationId":"station-003662","note":"歯科"},{"id":"medical-1-11961","name":"救世軍ブース記念病院","categoryId":"medical","categoryLabel":"医疗","lat":35.690383,"lng":139.660451,"stationId":"station-003688","note":"内科　消化器内科　内視鏡　循環器内科　漢方内科　精神科　神経内科　整形外科　眼科　皮膚科　リハビリ科"},{"id":"medical-2-15691","name":"整形外科峰岸クリニック","categoryId":"medical","categoryLabel":"医疗","lat":35.686043,"lng":139.670302,"stationId":"station-003688","note":"整形外科　理学診療科　麻酔科"},{"id":"medical-2-15261","name":"新中野内科クリニック","categoryId":"medical","categoryLabel":"医疗","lat":35.697275,"lng":139.669243,"stationId":"station-003638","note":"内科　消化器内科　胃腸内科"},{"id":"medical-2-15260","name":"新中野ＦＫクリニック","categoryId":"medical","categoryLabel":"医疗","lat":35.697181,"lng":139.666581,"stationId":"station-003638","note":"神経科　精神科　心療内科"},{"id":"medical-2-15145","name":"新宿　睡眠・呼吸器内科クリニック","categoryId":"medical","categoryLabel":"医疗","lat":35.692699,"lng":139.692504,"stationId":"station-003662","note":"内科　呼吸器内科"},{"id":"medical-2-15155","name":"新宿オークタワークリニック","categoryId":"medical","categoryLabel":"医疗","lat":35.693904,"lng":139.690625,"stationId":"station-003662","note":"内科　呼吸器内科　循環器内科　消化器内科　胃腸内科　外科"},{"id":"medical-2-15156","name":"新宿グリーンタワー内科クリニック","categoryId":"medical","categoryLabel":"医疗","lat":35.692293,"lng":139.689647,"stationId":"station-003690","note":"内科　精神科　呼吸器内科　循環器内科　糖尿病内科　代謝内科"},{"id":"medical-2-15163","name":"新宿ストレスクリニック本院","categoryId":"medical","categoryLabel":"医疗","lat":35.692699,"lng":139.692504,"stationId":"station-003662","note":"精神科　心療内科　神経内科"},{"id":"medical-3-15166","name":"新宿セントラルパーク歯科","categoryId":"medical","categoryLabel":"医疗","lat":35.690289,"lng":139.687517,"stationId":"station-003696","note":"歯科　小児歯科　矯正歯科　歯科口腔外科"},{"id":"medical-2-15213","name":"新宿住友クリニックセンター","categoryId":"medical","categoryLabel":"医疗","lat":35.69133,"lng":139.692871,"stationId":"station-003690","note":"内科　歯科"},{"id":"medical-3-15221","name":"新宿西参道歯科","categoryId":"medical","categoryLabel":"医疗","lat":35.684581,"lng":139.69023,"stationId":"station-003764","note":"歯科　歯科口腔外科　矯正歯科　小児歯科"},{"id":"medical-2-20435","name":"有川クリニック","categoryId":"medical","categoryLabel":"医疗","lat":35.69157,"lng":139.691072,"stationId":"station-003690","note":"内科"},{"id":"medical-2-20151","name":"木実谷医院","categoryId":"medical","categoryLabel":"医疗","lat":35.678746,"lng":139.667419,"stationId":"station-003806","note":"内科　小児科"},{"id":"medical-2-20179","name":"木村整形外科","categoryId":"medical","categoryLabel":"医疗","lat":35.680264,"lng":139.687254,"stationId":"station-003764","note":"理学診療科　内科　整形外科"},{"id":"medical-3-20030","name":"本町デンタルクリニック","categoryId":"medical","categoryLabel":"医疗","lat":35.682376,"lng":139.67878,"stationId":"station-003791","note":"歯科"},{"id":"medical-2-20036","name":"本町内科小児科クリニック","categoryId":"medical","categoryLabel":"医疗","lat":35.682931,"lng":139.683332,"stationId":"station-003764","note":"内科　小児科"},{"id":"medical-2-20032","name":"本町眼科クリニック","categoryId":"medical","categoryLabel":"医疗","lat":35.682931,"lng":139.683332,"stationId":"station-003764","note":"眼科"},{"id":"medical-3-20029","name":"本町５丁目歯科","categoryId":"medical","categoryLabel":"医疗","lat":35.692278,"lng":139.668694,"stationId":"station-003688","note":"歯科　小児歯科"},{"id":"medical-2-20006","name":"本郷診療所","categoryId":"medical","categoryLabel":"医疗","lat":35.694233,"lng":139.670665,"stationId":"station-003638","note":"内科"},{"id":"medical-3-15585","name":"杉田歯科医院","categoryId":"medical","categoryLabel":"医疗","lat":35.678776,"lng":139.677331,"stationId":"station-003791","note":"歯科　矯正歯科　小児歯科"},{"id":"medical-1-18148","name":"東京医科大学病院","categoryId":"medical","categoryLabel":"医疗","lat":35.693351,"lng":139.691862,"stationId":"station-003662","note":"内科　呼吸器内科　循環器内科　消化器内科　腎臓内科　神経内科　血液内科　糖尿病内分泌内科　皮膚科　リウマチ科　老年内科　小児科　精神科　外科　呼吸器外科　心臓血管外科　乳腺外科　消化器外科　泌尿器科　脳神経外科　整形外科　形成外科　眼科　耳鼻いんこう科"},{"id":"medical-2-18149","name":"東京医科大学病院　健診予防医学センター","categoryId":"medical","categoryLabel":"医疗","lat":35.692699,"lng":139.692504,"stationId":"station-003662","note":"内科　婦人科"},{"id":"medical-2-18234","name":"東京都交通局職員部労働課健康管理室","categoryId":"medical","categoryLabel":"医疗","lat":35.689238,"lng":139.691721,"stationId":"station-003690","note":"内科　精神科"},{"id":"medical-2-18240","name":"東京都職員共済組合シティ・ホール診療所","categoryId":"medical","categoryLabel":"医疗","lat":35.689238,"lng":139.691721,"stationId":"station-003690","note":"内科　皮膚科　外科　眼科　耳鼻いんこう科　歯科"},{"id":"medical-2-18255","name":"東京都赤十字血液センター都庁出張所","categoryId":"medical","categoryLabel":"医疗","lat":35.689238,"lng":139.691721,"stationId":"station-003690","note":"内科"},{"id":"medical-3-18414","name":"東條歯科医院","categoryId":"medical","categoryLabel":"医疗","lat":35.680995,"lng":139.686851,"stationId":"station-003764","note":"歯科"},{"id":"medical-3-18328","name":"東高円寺コムリセ歯科クリニック","categoryId":"medical","categoryLabel":"医疗","lat":35.697888,"lng":139.660832,"stationId":"station-003628","note":"歯科　矯正歯科　小児歯科　歯科口腔外科"},{"id":"medical-3-14862","name":"松本歯科医院","categoryId":"medical","categoryLabel":"医疗","lat":35.692142,"lng":139.673703,"stationId":"station-003679","note":"歯科　小児歯科"},{"id":"medical-2-19174","name":"板垣医院","categoryId":"medical","categoryLabel":"医疗","lat":35.677114,"lng":139.6675,"stationId":"station-003806","note":"内分泌内科　内科　糖尿病内科　代謝内科"},{"id":"medical-2-19036","name":"柏木クリニック","categoryId":"medical","categoryLabel":"医疗","lat":35.680775,"lng":139.686549,"stationId":"station-003764","note":"内科　循環器内科　リハビリテーション科"},{"id":"medical-2-20402","name":"柳田医院","categoryId":"medical","categoryLabel":"医疗","lat":35.689704,"lng":139.670648,"stationId":"station-003688","note":"内科　小児科"},{"id":"medical-2-11409","name":"株式会社　京王プラザホテル診療室","categoryId":"medical","categoryLabel":"医疗","lat":35.690146,"lng":139.694336,"stationId":"station-003690","note":"内科"},{"id":"medical-3-10951","name":"横江歯科医院","categoryId":"medical","categoryLabel":"医疗","lat":35.695389,"lng":139.69057,"stationId":"station-003662","note":"歯科"},{"id":"medical-2-12014","name":"橋本医院","categoryId":"medical","categoryLabel":"医疗","lat":35.680868,"lng":139.672931,"stationId":"station-003791","note":"内科　皮膚科"},{"id":"medical-3-19566","name":"武田歯科医院","categoryId":"medical","categoryLabel":"医疗","lat":35.678337,"lng":139.679706,"stationId":"station-003791","note":"歯科"},{"id":"medical-2-19574","name":"武藤医院","categoryId":"medical","categoryLabel":"医疗","lat":35.685084,"lng":139.683288,"stationId":"station-003696","note":"内科"},{"id":"medical-3-19577","name":"武藤歯科医院","categoryId":"medical","categoryLabel":"医疗","lat":35.676836,"lng":139.673956,"stationId":"station-003791","note":"歯科　矯正歯科　小児歯科　歯科口腔外科"},{"id":"medical-3-13888","name":"歯科口腔外科菊地クリニック","categoryId":"medical","categoryLabel":"医疗","lat":35.692682,"lng":139.691119,"stationId":"station-003662","note":"歯科　矯正歯科　小児歯科　歯科口腔外科"},{"id":"medical-3-13892","name":"歯科室　福田","categoryId":"medical","categoryLabel":"医疗","lat":35.685153,"lng":139.666676,"stationId":"station-003688","note":"歯科　歯科口腔外科　小児歯科"},{"id":"medical-3-13912","name":"歯科米沢医院","categoryId":"medical","categoryLabel":"医疗","lat":35.697446,"lng":139.680574,"stationId":"station-003643","note":"歯科"},{"id":"medical-2-15521","name":"水町クリニック","categoryId":"medical","categoryLabel":"医疗","lat":35.69157,"lng":139.691072,"stationId":"station-003690","note":"内科　脳神経外科　皮膚科　泌尿器科　眼科　整形外科"},{"id":"medical-2-15522","name":"水町保険診療所","categoryId":"medical","categoryLabel":"医疗","lat":35.69157,"lng":139.691072,"stationId":"station-003690","note":"内科　眼科　循環器内科　神経内科　婦人科　整形外科　精神科"},{"id":"medical-3-15538","name":"水野歯科医院","categoryId":"medical","categoryLabel":"医疗","lat":35.678663,"lng":139.665559,"stationId":"station-003806","note":"歯科　小児歯科"},{"id":"medical-2-10863","name":"永野医院","categoryId":"medical","categoryLabel":"医疗","lat":35.677911,"lng":139.678351,"stationId":"station-003791","note":"内科　皮膚科"},{"id":"medical-3-17256","name":"池田歯科医院","categoryId":"medical","categoryLabel":"医疗","lat":35.687156,"lng":139.677467,"stationId":"station-003679","note":"歯科"},{"id":"medical-3-17244","name":"池端歯科医院","categoryId":"medical","categoryLabel":"医疗","lat":35.678004,"lng":139.678666,"stationId":"station-003791","note":"歯科"},{"id":"medical-2-11217","name":"河崎外科胃腸科","categoryId":"medical","categoryLabel":"医疗","lat":35.693526,"lng":139.677475,"stationId":"station-003679","note":"内科　消化器科　胃腸科　皮膚科　小児科　肛門科　整形外科　放射線科　外科"},{"id":"medical-2-14358","name":"渋谷区あやめの苑・代々木医務室","categoryId":"medical","categoryLabel":"医疗","lat":35.682559,"lng":139.692936,"stationId":"station-003764","note":"内科　精神科　整形外科"},{"id":"medical-2-14360","name":"渋谷区つばめの里・本町東　医務室","categoryId":"medical","categoryLabel":"医疗","lat":35.687545,"lng":139.682171,"stationId":"station-003696","note":"内科"},{"id":"medical-2-14367","name":"渋谷区保健所幡ヶ谷保健相談所","categoryId":"medical","categoryLabel":"医疗","lat":35.67941,"lng":139.672057,"stationId":"station-003791","note":"内科　小児科"},{"id":"medical-2-14363","name":"渋谷区総合ケアコミュニティ・せせらぎ医務室","categoryId":"medical","categoryLabel":"医疗","lat":35.675314,"lng":139.68181,"stationId":"station-003791","note":"内科"},{"id":"medical-2-17900","name":"渡辺クリニック","categoryId":"medical","categoryLabel":"医疗","lat":35.688731,"lng":139.682768,"stationId":"station-003696","note":"内科"},{"id":"medical-2-17942","name":"渡辺整形外科・外科・内科","categoryId":"medical","categoryLabel":"医疗","lat":35.697703,"lng":139.682291,"stationId":"station-003643","note":"内科　外科　整形外科　乳腺外科　消化器内科　胃腸内科"},{"id":"medical-2-17914","name":"渡辺眼科医院","categoryId":"medical","categoryLabel":"医疗","lat":35.698385,"lng":139.675962,"stationId":"station-003638","note":"眼科"},{"id":"medical-3-17894","name":"渡部歯科","categoryId":"medical","categoryLabel":"医疗","lat":35.683494,"lng":139.667347,"stationId":"station-003688","note":"歯科　小児歯科"},{"id":"medical-2-14900","name":"湘南メディカルクリニック新宿院","categoryId":"medical","categoryLabel":"医疗","lat":35.694151,"lng":139.694729,"stationId":"station-003662","note":"内科　腫瘍内科　アレルギー科　呼吸器内科"},{"id":"medical-2-14914","name":"湘南美容クリニック新宿本院","categoryId":"medical","categoryLabel":"医疗","lat":35.692699,"lng":139.692504,"stationId":"station-003662","note":"美容外科　美容皮膚科　形成外科　呼吸器内科　アレルギー科"},{"id":"medical-2-12832","name":"溝口医院","categoryId":"medical","categoryLabel":"医疗","lat":35.692474,"lng":139.675589,"stationId":"station-003679","note":"内科　皮膚科　小児科"},{"id":"medical-2-19962","name":"牧野産婦人科クリニック","categoryId":"medical","categoryLabel":"医疗","lat":35.696432,"lng":139.682471,"stationId":"station-003643","note":"産婦人科"},{"id":"medical-2-18569","name":"特別養護老人ホーム　愛敬苑　医務室","categoryId":"medical","categoryLabel":"医疗","lat":35.689531,"lng":139.664167,"stationId":"station-003688","note":"内科"},{"id":"medical-2-18686","name":"独立行政法人　都市再生機構　新宿診療所","categoryId":"medical","categoryLabel":"医疗","lat":35.692699,"lng":139.692504,"stationId":"station-003662","note":"内科"},{"id":"medical-3-17754","name":"田口歯科医院","categoryId":"medical","categoryLabel":"医疗","lat":35.688308,"lng":139.688718,"stationId":"station-003696","note":"歯科　歯科口腔外科　小児歯科"},{"id":"medical-3-17743","name":"田賀歯科医院","categoryId":"medical","categoryLabel":"医疗","lat":35.677832,"lng":139.691552,"stationId":"station-003778","note":"歯科　矯正歯科　小児歯科　歯科口腔外科"},{"id":"medical-2-17747","name":"田郷内科胃腸科医院","categoryId":"medical","categoryLabel":"医疗","lat":35.692906,"lng":139.677426,"stationId":"station-003679","note":"内科　呼吸器科　循環器科　小児科　胃腸科"},{"id":"medical-3-19266","name":"番田歯科医院","categoryId":"medical","categoryLabel":"医疗","lat":35.681348,"lng":139.672918,"stationId":"station-003791","note":"歯科　矯正歯科　小児歯科"},{"id":"medical-2-19082","name":"白川クリニック","categoryId":"medical","categoryLabel":"医疗","lat":35.685313,"lng":139.66939,"stationId":"station-003688","note":"内科　内視鏡内科　消化器科　胃腸内科　外科　肛門外科"},{"id":"medical-2-19078","name":"白石医院","categoryId":"medical","categoryLabel":"医疗","lat":35.694387,"lng":139.683892,"stationId":"station-003643","note":"内科　外科　整形外科"},{"id":"medical-2-19079","name":"白石医院","categoryId":"medical","categoryLabel":"医疗","lat":35.683111,"lng":139.671517,"stationId":"station-003791","note":"内科　皮膚科　小児科　精神科　外科　泌尿器科　整形外科　産婦人科"},{"id":"medical-2-19276","name":"皮膚科こかじクリニック","categoryId":"medical","categoryLabel":"医疗","lat":35.685796,"lng":139.668259,"stationId":"station-003688","note":"皮膚科　アレルギー科"},{"id":"medical-3-12030","name":"矯正歯科シーシーデンタルオフィス","categoryId":"medical","categoryLabel":"医疗","lat":35.693763,"lng":139.694244,"stationId":"station-003662","note":"歯科　矯正歯科　小児歯科　歯科口腔外科"},{"id":"medical-3-16084","name":"石井歯科医院","categoryId":"medical","categoryLabel":"医疗","lat":35.695727,"lng":139.669416,"stationId":"station-003638","note":"歯科"},{"id":"medical-2-16113","name":"石崎耳鼻咽喉科医院","categoryId":"medical","categoryLabel":"医疗","lat":35.68157,"lng":139.687332,"stationId":"station-003764","note":"耳鼻いんこう科"},{"id":"medical-2-14095","name":"社会医療法人社団健友会　川島診療所","categoryId":"medical","categoryLabel":"医疗","lat":35.687493,"lng":139.672401,"stationId":"station-003679","note":"内科　循環器内科　胃腸内科　外科　整形外科　歯科"},{"id":"medical-2-14145","name":"社会福祉法人ケアネット　特別養護老人ホーム「弥生ホーム」","categoryId":"medical","categoryLabel":"医疗","lat":35.691913,"lng":139.672492,"stationId":"station-003679","note":"内科"},{"id":"medical-3-14273","name":"秋元歯科医院","categoryId":"medical","categoryLabel":"医疗","lat":35.694071,"lng":139.66822,"stationId":"station-003688","note":"歯科　小児歯科　歯科口腔外科"},{"id":"medical-2-14269","name":"秋吉クリニック","categoryId":"medical","categoryLabel":"医疗","lat":35.695976,"lng":139.675394,"stationId":"station-003679","note":"内科　循環器科"},{"id":"medical-3-14290","name":"秋庭歯科医院","categoryId":"medical","categoryLabel":"医疗","lat":35.689889,"lng":139.664036,"stationId":"station-003688","note":"歯科　小児歯科　歯科口腔外科"},{"id":"medical-3-20515","name":"立花歯科医院","categoryId":"medical","categoryLabel":"医疗","lat":35.697331,"lng":139.671159,"stationId":"station-003638","note":"歯科"},{"id":"medical-2-13394","name":"笹塚クリニック","categoryId":"medical","categoryLabel":"医疗","lat":35.675244,"lng":139.671137,"stationId":"station-003806","note":"循環器科　内科　小児科"},{"id":"medical-3-13400","name":"笹塚歯科","categoryId":"medical","categoryLabel":"医疗","lat":35.677324,"lng":139.669385,"stationId":"station-003806","note":"歯科　矯正歯科　小児歯科　歯科口腔外科"},{"id":"medical-2-13401","name":"笹塚清水眼科","categoryId":"medical","categoryLabel":"医疗","lat":35.675411,"lng":139.667971,"stationId":"station-003806","note":"眼科"},{"id":"medical-2-14023","name":"篠原クリニック","categoryId":"medical","categoryLabel":"医疗","lat":35.678114,"lng":139.666074,"stationId":"station-003806","note":"性病科　内科　産科　婦人科"},{"id":"medical-3-14025","name":"篠原歯科医院","categoryId":"medical","categoryLabel":"医疗","lat":35.678114,"lng":139.666074,"stationId":"station-003806","note":"歯科"},{"id":"medical-2-16602","name":"荘司医院","categoryId":"medical","categoryLabel":"医疗","lat":35.692559,"lng":139.683089,"stationId":"station-003696","note":"内科　外科　泌尿器科　理学診療科"},{"id":"medical-3-16645","name":"袖山歯科医院","categoryId":"medical","categoryLabel":"医疗","lat":35.679829,"lng":139.687442,"stationId":"station-003764","note":"歯科"},{"id":"medical-2-15864","name":"西新宿おざわメンタルクリニック","categoryId":"medical","categoryLabel":"医疗","lat":35.690608,"lng":139.68654,"stationId":"station-003696","note":"精神科　心療内科　内科"},{"id":"medical-3-15866","name":"西新宿デンタルクリニック","categoryId":"medical","categoryLabel":"医疗","lat":35.693753,"lng":139.689602,"stationId":"station-003662","note":"歯科"},{"id":"medical-3-15868","name":"西新宿五丁目くるみ歯科医院","categoryId":"medical","categoryLabel":"医疗","lat":35.689601,"lng":139.684372,"stationId":"station-003696","note":"歯科　矯正歯科　小児歯科　歯科口腔外科"},{"id":"medical-3-15869","name":"西新宿五丁目駅前歯科クリニック","categoryId":"medical","categoryLabel":"医疗","lat":35.689727,"lng":139.684563,"stationId":"station-003696","note":"歯科　小児歯科　矯正歯科"},{"id":"medical-3-15875","name":"西新宿令和クリニック","categoryId":"medical","categoryLabel":"医疗","lat":35.688074,"lng":139.693453,"stationId":"station-003690","note":"歯科　矯正歯科"},{"id":"medical-3-15871","name":"西新宿十二社歯科","categoryId":"medical","categoryLabel":"医疗","lat":35.693424,"lng":139.687282,"stationId":"station-003696","note":"歯科　矯正歯科　小児歯科　歯科口腔外科"},{"id":"medical-2-15872","name":"西新宿小林クリニック","categoryId":"medical","categoryLabel":"医疗","lat":35.693424,"lng":139.687282,"stationId":"station-003696","note":"内科　循環器内科　小児科"},{"id":"medical-2-15874","name":"西新宿整形外科クリニック","categoryId":"medical","categoryLabel":"医疗","lat":35.694151,"lng":139.694729,"stationId":"station-003662","note":"整形外科　美容皮膚科"},{"id":"medical-2-15863","name":"西新宿５丁目内山クリニック","categoryId":"medical","categoryLabel":"医疗","lat":35.689953,"lng":139.68238,"stationId":"station-003696","note":"内科　循環器内科　消化器内科　胃腸内科　皮膚科"},{"id":"medical-2-15862","name":"西新宿５丁目駅前眼科","categoryId":"medical","categoryLabel":"医疗","lat":35.690608,"lng":139.68654,"stationId":"station-003696","note":"眼科"},{"id":"medical-3-19831","name":"豊田歯科クリニック","categoryId":"medical","categoryLabel":"医疗","lat":35.688964,"lng":139.683016,"stationId":"station-003696","note":"歯科"},{"id":"medical-2-16244","name":"赤心堂クリニック","categoryId":"medical","categoryLabel":"医疗","lat":35.683206,"lng":139.691942,"stationId":"station-003764","note":"消化器科　こう門科　内科　小児科　外科"},{"id":"medical-2-17954","name":"都庁前血管外科・循環器内科","categoryId":"medical","categoryLabel":"医疗","lat":35.692652,"lng":139.690657,"stationId":"station-003662","note":"血管外科　循環器内科　漢方内科　糖尿病内科　内分泌外科"},{"id":"medical-2-14389","name":"重光クリニック","categoryId":"medical","categoryLabel":"医疗","lat":35.694099,"lng":139.674092,"stationId":"station-003679","note":"内科　外科　肛門科　胃腸科"},{"id":"medical-3-12120","name":"金子歯科医院","categoryId":"medical","categoryLabel":"医疗","lat":35.689694,"lng":139.67795,"stationId":"station-003679","note":"歯科"},{"id":"medical-3-12148","name":"金田歯科医院","categoryId":"medical","categoryLabel":"医疗","lat":35.683097,"lng":139.678882,"stationId":"station-003791","note":"歯科"},{"id":"medical-3-17580","name":"長井歯科医院","categoryId":"medical","categoryLabel":"医疗","lat":35.696659,"lng":139.664304,"stationId":"station-003638","note":"歯科"},{"id":"medical-3-17612","name":"長谷川歯科医院","categoryId":"medical","categoryLabel":"医疗","lat":35.684679,"lng":139.683144,"stationId":"station-003764","note":"歯科　小児歯科　歯科口腔外科"},{"id":"medical-2-18813","name":"難波眼科","categoryId":"medical","categoryLabel":"医疗","lat":35.688074,"lng":139.693453,"stationId":"station-003690","note":"眼科"},{"id":"medical-3-16024","name":"青木歯科","categoryId":"medical","categoryLabel":"医疗","lat":35.684864,"lng":139.685606,"stationId":"station-003764","note":"歯科　矯正歯科　小児歯科　歯科口腔外科"},{"id":"medical-2-18501","name":"頭とからだのクリニック　かねなか脳神経外科","categoryId":"medical","categoryLabel":"医疗","lat":35.697632,"lng":139.66888,"stationId":"station-003638","note":"脳神経外科　リハビリテーション科　放射線科　リウマチ科"},{"id":"medical-2-10864","name":"頴川医院","categoryId":"medical","categoryLabel":"医疗","lat":35.695962,"lng":139.678408,"stationId":"station-003643","note":"内科　小児科　産婦人科"},{"id":"medical-2-12253","name":"駒ヶ嶺医院","categoryId":"medical","categoryLabel":"医疗","lat":35.6897,"lng":139.685462,"stationId":"station-003696","note":"内科"},{"id":"medical-3-12972","name":"高市歯科医院","categoryId":"medical","categoryLabel":"医疗","lat":35.698053,"lng":139.675377,"stationId":"station-003638","note":"歯科　小児歯科"},{"id":"medical-3-12980","name":"高杉歯科クリニック","categoryId":"medical","categoryLabel":"医疗","lat":35.68844,"lng":139.681527,"stationId":"station-003696","note":"歯科"},{"id":"medical-2-13037","name":"高野整形外科","categoryId":"medical","categoryLabel":"医疗","lat":35.687346,"lng":139.670879,"stationId":"station-003688","note":"整形外科　理学診療科　リウマチ科"},{"id":"medical-3-82","name":"７Ｄｅｎｔａｌ　Ｃｌｉｎｉｃ","categoryId":"medical","categoryLabel":"医疗","lat":35.687336,"lng":139.675833,"stationId":"station-003679","note":"歯科　矯正歯科　小児歯科　歯科口腔外科"},{"id":"medical-3-123","name":"ＡＺデンタルクリニック笹塚","categoryId":"medical","categoryLabel":"医疗","lat":35.675689,"lng":139.670667,"stationId":"station-003806","note":"歯科　矯正歯科　小児歯科　歯科口腔外科"},{"id":"medical-3-318","name":"Ｓ＆Ａ　ＤＥＮＴＡＬ　ＣＬＩＮＩＣ","categoryId":"medical","categoryLabel":"医疗","lat":35.696596,"lng":139.691737,"stationId":"station-003662","note":"歯科　矯正歯科　小児歯科　歯科口腔外科"},{"id":"medical-2-329","name":"Ｓｈｉｎｊｕｋｕ　ＡＲＴ　Ｃｌｉｎｉｃ","categoryId":"medical","categoryLabel":"医疗","lat":35.693904,"lng":139.690625,"stationId":"station-003662","note":"婦人科　産科　泌尿器科"},{"id":"medical-3-339","name":"Ｔ．Ｏ．Ｐ．Ｓ．　ＤＥＮＴＡＬ　ＣＬＩＮＩＣ","categoryId":"medical","categoryLabel":"医疗","lat":35.688731,"lng":139.682768,"stationId":"station-003696","note":"歯科　矯正歯科　小児歯科　歯科口腔外科"},{"id":"medical-2-362","name":"ＴＭクリニック西新宿","categoryId":"medical","categoryLabel":"医疗","lat":35.697164,"lng":139.690402,"stationId":"station-003662","note":"皮膚科　内科"},{"id":"public-13114-21782","name":"しんやまの家","categoryId":"public_service","categoryLabel":"公共服务","lat":35.680775,"lng":139.667682,"stationId":"station-003806","note":"中野区南台4-25-1"},{"id":"public-13113-21714","name":"はつらつセンター参宮橋","categoryId":"public_service","categoryLabel":"公共服务","lat":35.678807,"lng":139.693069,"stationId":"station-003778","note":"渋谷区代々木4-4-1"},{"id":"public-13113-21721","name":"はつらつセンター幡ヶ谷","categoryId":"public_service","categoryLabel":"公共服务","lat":35.677366,"lng":139.674086,"stationId":"station-003791","note":"渋谷区幡ヶ谷2-19-14"},{"id":"public-13113-21666","name":"シニア・いきいきコミュニティせせらぎ","categoryId":"public_service","categoryLabel":"公共服务","lat":35.675289,"lng":139.681831,"stationId":"station-003791","note":"渋谷区西原1-40-10"},{"id":"public-13113-21713","name":"代々木四丁目施設","categoryId":"public_service","categoryLabel":"公共服务","lat":35.68148,"lng":139.692493,"stationId":"station-003778","note":"渋谷区代々木4-23-12"},{"id":"public-13113-21685","name":"児童青少年センターフレンズ本町","categoryId":"public_service","categoryLabel":"公共服务","lat":35.682102,"lng":139.679558,"stationId":"station-003791","note":"渋谷区本町6-6-2"},{"id":"public-13113-21687","name":"初台出張所","categoryId":"public_service","categoryLabel":"公共服务","lat":35.679639,"lng":139.684849,"stationId":"station-003764","note":"渋谷区初台1-33-10"},{"id":"public-13113-21690","name":"初台区民会館","categoryId":"public_service","categoryLabel":"公共服务","lat":35.679618,"lng":139.684818,"stationId":"station-003764","note":"渋谷区初台1-33-10"},{"id":"public-13113-21689","name":"初台青年館","categoryId":"public_service","categoryLabel":"公共服务","lat":35.679607,"lng":139.684773,"stationId":"station-003764","note":"渋谷区初台1-33-10"},{"id":"public-13114-21788","name":"南中野区民活動センター","categoryId":"public_service","categoryLabel":"公共服务","lat":35.685974,"lng":139.666507,"stationId":"station-003688","note":"中野区弥生町5-5-2"},{"id":"public-13114-21789","name":"南中野地域包括支援センター","categoryId":"public_service","categoryLabel":"公共服务","lat":35.68811,"lng":139.668856,"stationId":"station-003688","note":"中野区弥生町5-11-26"},{"id":"public-13114-21790","name":"南部すこやか福祉センター","categoryId":"public_service","categoryLabel":"公共服务","lat":35.68808,"lng":139.668846,"stationId":"station-003688","note":"中野区弥生町5-11-26"},{"id":"public-13114-21783","name":"南部高齢者会館","categoryId":"public_service","categoryLabel":"公共服务","lat":35.68327,"lng":139.660998,"stationId":"station-003751","note":"中野区南台5-27-24"},{"id":"public-13113-21719","name":"地域交流センター二軒家","categoryId":"public_service","categoryLabel":"公共服务","lat":35.689246,"lng":139.681163,"stationId":"station-003696","note":"渋谷区本町3-35-4"},{"id":"public-13113-21730","name":"地域交流センター本町","categoryId":"public_service","categoryLabel":"公共服务","lat":35.682102,"lng":139.679538,"stationId":"station-003791","note":"渋谷区本町6-6-2児童青少年センター複合施設2F"},{"id":"public-13114-21750","name":"子ども・若者支援センター","categoryId":"public_service","categoryLabel":"公共服务","lat":35.698292,"lng":139.683185,"stationId":"station-003643","note":"中野区中央1-41-2"},{"id":"public-13113-21724","name":"幡ケ谷二丁目施設","categoryId":"public_service","categoryLabel":"公共服务","lat":35.67914,"lng":139.67522,"stationId":"station-003791","note":"渋谷区幡ケ谷2-53-7"},{"id":"public-13113-21725","name":"幡ヶ谷三丁目施設","categoryId":"public_service","categoryLabel":"公共服务","lat":35.679416,"lng":139.672009,"stationId":"station-003791","note":"渋谷区幡ヶ谷3-39-1"},{"id":"public-13113-21726","name":"幡ヶ谷区民会館","categoryId":"public_service","categoryLabel":"公共服务","lat":35.679783,"lng":139.675983,"stationId":"station-003791","note":"渋谷区幡ヶ谷3-4-1"},{"id":"public-13113-21723","name":"幡ヶ谷社会教育館","categoryId":"public_service","categoryLabel":"公共服务","lat":35.679872,"lng":139.677306,"stationId":"station-003791","note":"渋谷区幡ヶ谷2-50-2"},{"id":"public-13114-21799","name":"弥生区民活動センター","categoryId":"public_service","categoryLabel":"公共服务","lat":35.692505,"lng":139.678424,"stationId":"station-003679","note":"中野区弥生町1-58-14"},{"id":"public-13114-21787","name":"本一高齢者会館","categoryId":"public_service","categoryLabel":"公共服务","lat":35.693695,"lng":139.68259,"stationId":"station-003643","note":"中野区本町1-7-6"},{"id":"public-13113-21729","name":"本町一丁目施設","categoryId":"public_service","categoryLabel":"公共服务","lat":35.679835,"lng":139.681302,"stationId":"station-003791","note":"渋谷区本町1-15-13"},{"id":"public-13113-21732","name":"本町出張所","categoryId":"public_service","categoryLabel":"公共服务","lat":35.686785,"lng":139.680669,"stationId":"station-003696","note":"渋谷区本町4-9-7"},{"id":"public-13113-21731","name":"本町区民会館","categoryId":"public_service","categoryLabel":"公共服务","lat":35.686785,"lng":139.680689,"stationId":"station-003696","note":"渋谷区本町4-9-7"},{"id":"public-13114-21795","name":"本町地域包括支援センター","categoryId":"public_service","categoryLabel":"公共服务","lat":35.69268,"lng":139.673144,"stationId":"station-003679","note":"中野区本町5-10-4"},{"id":"public-13104-21020","name":"柏木地域センター","categoryId":"public_service","categoryLabel":"公共服务","lat":35.698511,"lng":139.690294,"stationId":"station-003662","note":"新宿区北新宿2-3-7"},{"id":"public-13104-21021","name":"柏木特別出張所","categoryId":"public_service","categoryLabel":"公共服务","lat":35.698511,"lng":139.690274,"stationId":"station-003662","note":"新宿区北新宿2-3-7"},{"id":"public-13104-20994","name":"産業会館ＢＩＺ新宿","categoryId":"public_service","categoryLabel":"公共服务","lat":35.693404,"lng":139.690426,"stationId":"station-003662","note":"新宿区西新宿6-8-2"},{"id":"public-13113-21678","name":"笹塚一丁目施設","categoryId":"public_service","categoryLabel":"公共服务","lat":35.675025,"lng":139.671148,"stationId":"station-003806","note":"渋谷区笹塚1-50-16"},{"id":"public-13113-21682","name":"笹塚三丁目施設","categoryId":"public_service","categoryLabel":"公共服务","lat":35.675783,"lng":139.665151,"stationId":"station-003806","note":"渋谷区笹塚3-22-10"},{"id":"public-13113-21680","name":"笹塚出張所","categoryId":"public_service","categoryLabel":"公共服务","lat":35.677605,"lng":139.670084,"stationId":"station-003806","note":"渋谷区笹塚3-1-9"},{"id":"public-13113-21679","name":"笹塚区民会館","categoryId":"public_service","categoryLabel":"公共服务","lat":35.677605,"lng":139.670104,"stationId":"station-003806","note":"渋谷区笹塚3-1-9"},{"id":"public-13113-21681","name":"笹塚十号坂施設","categoryId":"public_service","categoryLabel":"公共服务","lat":35.677308,"lng":139.666976,"stationId":"station-003806","note":"渋谷区笹塚3-19-2"},{"id":"public-13104-20993","name":"西新宿シニア活動館","categoryId":"public_service","categoryLabel":"公共服务","lat":35.688671,"lng":139.684305,"stationId":"station-003696","note":"新宿区西新宿4-8-35"},{"id":"public-13104-20975","name":"角筈地域センター","categoryId":"public_service","categoryLabel":"公共服务","lat":35.68621,"lng":139.689087,"stationId":"station-003764","note":"新宿区西新宿4-33-7"},{"id":"public-13104-20992","name":"角筈特別出張所","categoryId":"public_service","categoryLabel":"公共服务","lat":35.686196,"lng":139.689099,"stationId":"station-003764","note":"新宿区西新宿4-33-7"},{"id":"public-13114-21784","name":"鍋横区民活動センター","categoryId":"public_service","categoryLabel":"公共服务","lat":35.693722,"lng":139.667956,"stationId":"station-003688","note":"中野区本町5-47-13"},{"id":"public-13114-21786","name":"鍋横区民活動センター分室","categoryId":"public_service","categoryLabel":"公共服务","lat":35.696465,"lng":139.669482,"stationId":"station-003638","note":"中野区本町4-44-3"},{"id":"public-13113-21673","name":"スポーツセンター","categoryId":"sports","categoryLabel":"体育设施","lat":35.675623,"lng":139.681274,"stationId":"station-003791","note":"渋谷区西原1-40-18"},{"id":"public-13113-21703","name":"スポーツセンター体育館","categoryId":"sports","categoryLabel":"体育设施","lat":35.675925,"lng":139.680636,"stationId":"station-003791","note":"渋谷区西原1-40-18"},{"id":"public-13114-21793","name":"南部スポーツ・コミュニティプラザ","categoryId":"sports","categoryLabel":"体育设施","lat":35.68808,"lng":139.668826,"stationId":"station-003688","note":"中野区弥生町5-11-26"}]
