[{"id":"533936643","name":"人口mesh 533936643","categoryId":"增长","categoryLabel":"增长","summary":"2020→2040 变化率 27.9%","stationIds":["station-004034"],"metricValue":27.9,"metricLabel":"2040较2020","geometry":{"type":"Polygon","coordinates":[[[139.8,35.6375],[139.8,35.641667],[139.80625,35.641667],[139.80625,35.6375],[139.8,35.6375]]]}},{"id":"533936742","name":"人口mesh 533936742","categoryId":"收缩","categoryLabel":"收缩","summary":"2020→2040 变化率 -60.3%","stationIds":["station-003999"],"metricValue":-60.3,"metricLabel":"2040较2020","geometry":{"type":"Polygon","coordinates":[[[139.80625,35.641667],[139.80625,35.645833],[139.8125,35.645833],[139.8125,35.641667],[139.80625,35.641667]]]}}]
